{"ref":"410d27fc-9898-469f-beee-41f0345a032c","content":"{\"version\":1,\"machineId\":\"91b0b45e-7b9a-4e76-a190-5c1145b8c007\",\"content\":\"{\\\"storage\\\":{\\\"colorThemeData\\\":{\\\"version\\\":1,\\\"value\\\":\\\"{\\\\\\\"id\\\\\\\":\\\\\\\"vs vscode-theme-solarized-light-themes-solarized-light-color-theme-json\\\\\\\",\\\\\\\"label\\\\\\\":\\\\\\\"Solarized Light\\\\\\\",\\\\\\\"settingsId\\\\\\\":\\\\\\\"Solarized Light\\\\\\\",\\\\\\\"themeTokenColors\\\\\\\":[{\\\\\\\"settings\\\\\\\":{\\\\\\\"foreground\\\\\\\":\\\\\\\"#657B83\\\\\\\"}},{\\\\\\\"settings\\\\\\\":{\\\\\\\"foreground\\\\\\\":\\\\\\\"#657B83\\\\\\\"},\\\\\\\"scope\\\\\\\":[\\\\\\\"meta.embedded\\\\\\\",\\\\\\\"source.groovy.embedded\\\\\\\"]},{\\\\\\\"settings\\\\\\\":{\\\\\\\"fontStyle\\\\\\\":\\\\\\\"italic\\\\\\\",\\\\\\\"foreground\\\\\\\":\\\\\\\"#93A1A1\\\\\\\"},\\\\\\\"scope\\\\\\\":\\\\\\\"comment\\\\\\\"},{\\\\\\\"settings\\\\\\\":{\\\\\\\"foreground\\\\\\\":\\\\\\\"#2AA198\\\\\\\"},\\\\\\\"scope\\\\\\\":\\\\\\\"string\\\\\\\"},{\\\\\\\"settings\\\\\\\":{\\\\\\\"foreground\\\\\\\":\\\\\\\"#D30102\\\\\\\"},\\\\\\\"scope\\\\\\\":\\\\\\\"string.regexp\\\\\\\"},{\\\\\\\"settings\\\\\\\":{\\\\\\\"foreground\\\\\\\":\\\\\\\"#D33682\\\\\\\"},\\\\\\\"scope\\\\\\\":\\\\\\\"constant.numeric\\\\\\\"},{\\\\\\\"settings\\\\\\\":{\\\\\\\"foreground\\\\\\\":\\\\\\\"#268BD2\\\\\\\"},\\\\\\\"scope\\\\\\\":[\\\\\\\"variable.language\\\\\\\",\\\\\\\"variable.other\\\\\\\"]},{\\\\\\\"settings\\\\\\\":{\\\\\\\"foreground\\\\\\\":\\\\\\\"#859900\\\\\\\"},\\\\\\\"scope\\\\\\\":\\\\\\\"keyword\\\\\\\"},{\\\\\\\"settings\\\\\\\":{\\\\\\\"fontStyle\\\\\\\":\\\\\\\"bold\\\\\\\",\\\\\\\"foreground\\\\\\\":\\\\\\\"#073642\\\\\\\"},\\\\\\\"scope\\\\\\\":\\\\\\\"storage\\\\\\\"},{\\\\\\\"settings\\\\\\\":{\\\\\\\"foreground\\\\\\\":\\\\\\\"#268BD2\\\\\\\"},\\\\\\\"scope\\\\\\\":[\\\\\\\"entity.name.class\\\\\\\",\\\\\\\"entity.name.type\\\\\\\",\\\\\\\"entity.name.namespace\\\\\\\",\\\\\\\"entity.name.scope-resolution\\\\\\\"]},{\\\\\\\"settings\\\\\\\":{\\\\\\\"foreground\\\\\\\":\\\\\\\"#268BD2\\\\\\\"},\\\\\\\"scope\\\\\\\":\\\\\\\"entity.name.function\\\\\\\"},{\\\\\\\"settings\\\\\\\":{\\\\\\\"foreground\\\\\\\":\\\\\\\"#859900\\\\\\\"},\\\\\\\"scope\\\\\\\":\\\\\\\"punctuation.definition.variable\\\\\\\"},{\\\\\\\"settings\\\\\\\":{\\\\\\\"foreground\\\\\\\":\\\\\\\"#D30102\\\\\\\"},\\\\\\\"scope\\\\\\\":[\\\\\\\"punctuation.section.embedded.begin\\\\\\\",\\\\\\\"punctuation.section.embedded.end\\\\\\\"]},{\\\\\\\"settings\\\\\\\":{\\\\\\\"foreground\\\\\\\":\\\\\\\"#B58900\\\\\\\"},\\\\\\\"scope\\\\\\\":[\\\\\\\"constant.language\\\\\\\",\\\\\\\"meta.preprocessor\\\\\\\"]},{\\\\\\\"settings\\\\\\\":{\\\\\\\"foreground\\\\\\\":\\\\\\\"#D30102\\\\\\\"},\\\\\\\"scope\\\\\\\":[\\\\\\\"support.function.construct\\\\\\\",\\\\\\\"keyword.other.new\\\\\\\"]},{\\\\\\\"settings\\\\\\\":{\\\\\\\"foreground\\\\\\\":\\\\\\\"#CB4B16\\\\\\\"},\\\\\\\"scope\\\\\\\":[\\\\\\\"constant.character\\\\\\\",\\\\\\\"constant.other\\\\\\\"]},{\\\\\\\"settings\\\\\\\":{},\\\\\\\"scope\\\\\\\":\\\\\\\"entity.other.inherited-class\\\\\\\"},{\\\\\\\"settings\\\\\\\":{},\\\\\\\"scope\\\\\\\":\\\\\\\"variable.parameter\\\\\\\"},{\\\\\\\"settings\\\\\\\":{\\\\\\\"foreground\\\\\\\":\\\\\\\"#268BD2\\\\\\\"},\\\\\\\"scope\\\\\\\":\\\\\\\"entity.name.tag\\\\\\\"},{\\\\\\\"settings\\\\\\\":{\\\\\\\"foreground\\\\\\\":\\\\\\\"#93A1A1\\\\\\\"},\\\\\\\"scope\\\\\\\":[\\\\\\\"punctuation.definition.tag.begin\\\\\\\",\\\\\\\"punctuation.definition.tag.end\\\\\\\"]},{\\\\\\\"settings\\\\\\\":{\\\\\\\"foreground\\\\\\\":\\\\\\\"#93A1A1\\\\\\\"},\\\\\\\"scope\\\\\\\":\\\\\\\"entity.other.attribute-name\\\\\\\"},{\\\\\\\"settings\\\\\\\":{\\\\\\\"foreground\\\\\\\":\\\\\\\"#268BD2\\\\\\\"},\\\\\\\"scope\\\\\\\":\\\\\\\"support.function\\\\\\\"},{\\\\\\\"settings\\\\\\\":{\\\\\\\"foreground\\\\\\\":\\\\\\\"#D30102\\\\\\\"},\\\\\\\"scope\\\\\\\":\\\\\\\"punctuation.separator.continuation\\\\\\\"},{\\\\\\\"settings\\\\\\\":{},\\\\\\\"scope\\\\\\\":[\\\\\\\"support.constant\\\\\\\",\\\\\\\"support.variable\\\\\\\"]},{\\\\\\\"settings\\\\\\\":{\\\\\\\"foreground\\\\\\\":\\\\\\\"#859900\\\\\\\"},\\\\\\\"scope\\\\\\\":[\\\\\\\"support.type\\\\\\\",\\\\\\\"support.class\\\\\\\"]},{\\\\\\\"settings\\\\\\\":{\\\\\\\"foreground\\\\\\\":\\\\\\\"#CB4B16\\\\\\\"},\\\\\\\"scope\\\\\\\":\\\\\\\"support.type.exception\\\\\\\"},{\\\\\\\"settings\\\\\\\":{},\\\\\\\"scope\\\\\\\":\\\\\\\"support.other.variable\\\\\\\"},{\\\\\\\"settings\\\\\\\":{\\\\\\\"foreground\\\\\\\":\\\\\\\"#cd3131\\\\\\\"},\\\\\\\"scope\\\\\\\":\\\\\\\"invalid\\\\\\\"},{\\\\\\\"settings\\\\\\\":{\\\\\\\"fontStyle\\\\\\\":\\\\\\\"italic\\\\\\\",\\\\\\\"foreground\\\\\\\":\\\\\\\"#268bd2\\\\\\\"},\\\\\\\"scope\\\\\\\":[\\\\\\\"meta.diff\\\\\\\",\\\\\\\"meta.diff.header\\\\\\\"]},{\\\\\\\"settings\\\\\\\":{\\\\\\\"fontStyle\\\\\\\":\\\\\\\"\\\\\\\",\\\\\\\"foreground\\\\\\\":\\\\\\\"#dc322f\\\\\\\"},\\\\\\\"scope\\\\\\\":\\\\\\\"markup.deleted\\\\\\\"},{\\\\\\\"settings\\\\\\\":{\\\\\\\"fontStyle\\\\\\\":\\\\\\\"\\\\\\\",\\\\\\\"foreground\\\\\\\":\\\\\\\"#cb4b16\\\\\\\"},\\\\\\\"scope\\\\\\\":\\\\\\\"markup.changed\\\\\\\"},{\\\\\\\"settings\\\\\\\":{\\\\\\\"foreground\\\\\\\":\\\\\\\"#219186\\\\\\\"},\\\\\\\"scope\\\\\\\":\\\\\\\"markup.inserted\\\\\\\"},{\\\\\\\"settings\\\\\\\":{\\\\\\\"foreground\\\\\\\":\\\\\\\"#859900\\\\\\\"},\\\\\\\"scope\\\\\\\":\\\\\\\"markup.quote\\\\\\\"},{\\\\\\\"settings\\\\\\\":{\\\\\\\"foreground\\\\\\\":\\\\\\\"#B58900\\\\\\\"},\\\\\\\"scope\\\\\\\":\\\\\\\"markup.list\\\\\\\"},{\\\\\\\"settings\\\\\\\":{\\\\\\\"foreground\\\\\\\":\\\\\\\"#D33682\\\\\\\"},\\\\\\\"scope\\\\\\\":[\\\\\\\"markup.bold\\\\\\\",\\\\\\\"markup.italic\\\\\\\"]},{\\\\\\\"settings\\\\\\\":{\\\\\\\"fontStyle\\\\\\\":\\\\\\\"bold\\\\\\\"},\\\\\\\"scope\\\\\\\":\\\\\\\"markup.bold\\\\\\\"},{\\\\\\\"settings\\\\\\\":{\\\\\\\"fontStyle\\\\\\\":\\\\\\\"italic\\\\\\\"},\\\\\\\"scope\\\\\\\":\\\\\\\"markup.italic\\\\\\\"},{\\\\\\\"settings\\\\\\\":{\\\\\\\"fontStyle\\\\\\\":\\\\\\\"\\\\\\\",\\\\\\\"foreground\\\\\\\":\\\\\\\"#2AA198\\\\\\\"},\\\\\\\"scope\\\\\\\":\\\\\\\"markup.inline.raw\\\\\\\"},{\\\\\\\"settings\\\\\\\":{\\\\\\\"fontStyle\\\\\\\":\\\\\\\"bold\\\\\\\",\\\\\\\"foreground\\\\\\\":\\\\\\\"#268BD2\\\\\\\"},\\\\\\\"scope\\\\\\\":\\\\\\\"markup.heading\\\\\\\"},{\\\\\\\"settings\\\\\\\":{\\\\\\\"fontStyle\\\\\\\":\\\\\\\"\\\\\\\",\\\\\\\"foreground\\\\\\\":\\\\\\\"#268BD2\\\\\\\"},\\\\\\\"scope\\\\\\\":\\\\\\\"markup.heading.setext\\\\\\\"}],\\\\\\\"semanticTokenRules\\\\\\\":[],\\\\\\\"extensionData\\\\\\\":{\\\\\\\"_extensionId\\\\\\\":\\\\\\\"vscode.theme-solarized-light\\\\\\\",\\\\\\\"_extensionIsBuiltin\\\\\\\":true,\\\\\\\"_extensionName\\\\\\\":\\\\\\\"theme-solarized-light\\\\\\\",\\\\\\\"_extensionPublisher\\\\\\\":\\\\\\\"vscode\\\\\\\"},\\\\\\\"themeSemanticHighlighting\\\\\\\":true,\\\\\\\"colorMap\\\\\\\":{\\\\\\\"focusBorder\\\\\\\":\\\\\\\"#d3af86\\\\\\\",\\\\\\\"input.background\\\\\\\":\\\\\\\"#ddd6c1\\\\\\\",\\\\\\\"input.foreground\\\\\\\":\\\\\\\"#586e75\\\\\\\",\\\\\\\"input.placeholderForeground\\\\\\\":\\\\\\\"#586e75aa\\\\\\\",\\\\\\\"inputOption.activeBorder\\\\\\\":\\\\\\\"#d3af86\\\\\\\",\\\\\\\"badge.background\\\\\\\":\\\\\\\"#b58900aa\\\\\\\",\\\\\\\"progressBar.background\\\\\\\":\\\\\\\"#b58900\\\\\\\",\\\\\\\"dropdown.background\\\\\\\":\\\\\\\"#eee8d5\\\\\\\",\\\\\\\"dropdown.border\\\\\\\":\\\\\\\"#d3af86\\\\\\\",\\\\\\\"button.background\\\\\\\":\\\\\\\"#ac9d57\\\\\\\",\\\\\\\"selection.background\\\\\\\":\\\\\\\"#ccc4b0\\\\\\\",\\\\\\\"list.activeSelectionBackground\\\\\\\":\\\\\\\"#dfca88\\\\\\\",\\\\\\\"list.activeSelectionForeground\\\\\\\":\\\\\\\"#6c6c6c\\\\\\\",\\\\\\\"list.focusBackground\\\\\\\":\\\\\\\"#dfca8866\\\\\\\",\\\\\\\"list.hoverBackground\\\\\\\":\\\\\\\"#dfca8844\\\\\\\",\\\\\\\"list.inactiveSelectionBackground\\\\\\\":\\\\\\\"#d1cbb8\\\\\\\",\\\\\\\"list.highlightForeground\\\\\\\":\\\\\\\"#b58900\\\\\\\",\\\\\\\"editor.background\\\\\\\":\\\\\\\"#fdf6e3\\\\\\\",\\\\\\\"editorWidget.background\\\\\\\":\\\\\\\"#eee8d5\\\\\\\",\\\\\\\"editorCursor.foreground\\\\\\\":\\\\\\\"#657b83\\\\\\\",\\\\\\\"editorWhitespace.foreground\\\\\\\":\\\\\\\"#586e7580\\\\\\\",\\\\\\\"editor.lineHighlightBackground\\\\\\\":\\\\\\\"#eee8d5\\\\\\\",\\\\\\\"editor.selectionBackground\\\\\\\":\\\\\\\"#eee8d5\\\\\\\",\\\\\\\"minimap.selectionHighlight\\\\\\\":\\\\\\\"#eee8d5\\\\\\\",\\\\\\\"editorIndentGuide.background\\\\\\\":\\\\\\\"#586e7580\\\\\\\",\\\\\\\"editorIndentGuide.activeBackground\\\\\\\":\\\\\\\"#081e2580\\\\\\\",\\\\\\\"editorHoverWidget.background\\\\\\\":\\\\\\\"#ccc4b0\\\\\\\",\\\\\\\"editorLineNumber.activeForeground\\\\\\\":\\\\\\\"#567983\\\\\\\",\\\\\\\"peekViewResult.background\\\\\\\":\\\\\\\"#eee8d5\\\\\\\",\\\\\\\"peekViewEditor.background\\\\\\\":\\\\\\\"#fffbf2\\\\\\\",\\\\\\\"peekViewTitle.background\\\\\\\":\\\\\\\"#eee8d5\\\\\\\",\\\\\\\"peekView.border\\\\\\\":\\\\\\\"#b58900\\\\\\\",\\\\\\\"peekViewEditor.matchHighlightBackground\\\\\\\":\\\\\\\"#7744aa40\\\\\\\",\\\\\\\"titleBar.activeBackground\\\\\\\":\\\\\\\"#eee8d5\\\\\\\",\\\\\\\"editorGroup.border\\\\\\\":\\\\\\\"#ddd6c1\\\\\\\",\\\\\\\"editorGroup.dropBackground\\\\\\\":\\\\\\\"#ddd6c1aa\\\\\\\",\\\\\\\"editorGroupHeader.tabsBackground\\\\\\\":\\\\\\\"#d9d2c2\\\\\\\",\\\\\\\"tab.border\\\\\\\":\\\\\\\"#ddd6c1\\\\\\\",\\\\\\\"tab.activeBackground\\\\\\\":\\\\\\\"#fdf6e3\\\\\\\",\\\\\\\"tab.inactiveForeground\\\\\\\":\\\\\\\"#586e75\\\\\\\",\\\\\\\"tab.inactiveBackground\\\\\\\":\\\\\\\"#d3cbb7\\\\\\\",\\\\\\\"tab.activeModifiedBorder\\\\\\\":\\\\\\\"#cb4b16\\\\\\\",\\\\\\\"tab.lastPinnedBorder\\\\\\\":\\\\\\\"#fdf6e3\\\\\\\",\\\\\\\"activityBar.background\\\\\\\":\\\\\\\"#ddd6c1\\\\\\\",\\\\\\\"activityBar.foreground\\\\\\\":\\\\\\\"#584c27\\\\\\\",\\\\\\\"activityBarBadge.background\\\\\\\":\\\\\\\"#b58900\\\\\\\",\\\\\\\"panel.border\\\\\\\":\\\\\\\"#ddd6c1\\\\\\\",\\\\\\\"sideBar.background\\\\\\\":\\\\\\\"#eee8d5\\\\\\\",\\\\\\\"sideBarTitle.foreground\\\\\\\":\\\\\\\"#586e75\\\\\\\",\\\\\\\"statusBar.foreground\\\\\\\":\\\\\\\"#586e75\\\\\\\",\\\\\\\"statusBar.background\\\\\\\":\\\\\\\"#eee8d5\\\\\\\",\\\\\\\"statusBar.debuggingBackground\\\\\\\":\\\\\\\"#eee8d5\\\\\\\",\\\\\\\"statusBar.noFolderBackground\\\\\\\":\\\\\\\"#eee8d5\\\\\\\",\\\\\\\"statusBarItem.remoteBackground\\\\\\\":\\\\\\\"#ac9d57\\\\\\\",\\\\\\\"statusBarItem.prominentBackground\\\\\\\":\\\\\\\"#ddd6c1\\\\\\\",\\\\\\\"statusBarItem.prominentHoverBackground\\\\\\\":\\\\\\\"#ddd6c199\\\\\\\",\\\\\\\"debugToolBar.background\\\\\\\":\\\\\\\"#ddd6c1\\\\\\\",\\\\\\\"debugExceptionWidget.background\\\\\\\":\\\\\\\"#ddd6c1\\\\\\\",\\\\\\\"debugExceptionWidget.border\\\\\\\":\\\\\\\"#ab395b\\\\\\\",\\\\\\\"pickerGroup.border\\\\\\\":\\\\\\\"#2aa19899\\\\\\\",\\\\\\\"pickerGroup.foreground\\\\\\\":\\\\\\\"#2aa19899\\\\\\\",\\\\\\\"extensionButton.prominentBackground\\\\\\\":\\\\\\\"#b58900\\\\\\\",\\\\\\\"extensionButton.prominentHoverBackground\\\\\\\":\\\\\\\"#584c27aa\\\\\\\",\\\\\\\"terminal.ansiBlack\\\\\\\":\\\\\\\"#073642\\\\\\\",\\\\\\\"terminal.ansiRed\\\\\\\":\\\\\\\"#dc322f\\\\\\\",\\\\\\\"terminal.ansiGreen\\\\\\\":\\\\\\\"#859900\\\\\\\",\\\\\\\"terminal.ansiYellow\\\\\\\":\\\\\\\"#b58900\\\\\\\",\\\\\\\"terminal.ansiBlue\\\\\\\":\\\\\\\"#268bd2\\\\\\\",\\\\\\\"terminal.ansiMagenta\\\\\\\":\\\\\\\"#d33682\\\\\\\",\\\\\\\"terminal.ansiCyan\\\\\\\":\\\\\\\"#2aa198\\\\\\\",\\\\\\\"terminal.ansiWhite\\\\\\\":\\\\\\\"#eee8d5\\\\\\\",\\\\\\\"terminal.ansiBrightBlack\\\\\\\":\\\\\\\"#586e75\\\\\\\",\\\\\\\"terminal.ansiBrightRed\\\\\\\":\\\\\\\"#cb4b16\\\\\\\",\\\\\\\"terminal.ansiBrightGreen\\\\\\\":\\\\\\\"#586e75\\\\\\\",\\\\\\\"terminal.ansiBrightYellow\\\\\\\":\\\\\\\"#657b83\\\\\\\",\\\\\\\"terminal.ansiBrightBlue\\\\\\\":\\\\\\\"#839496\\\\\\\",\\\\\\\"terminal.ansiBrightMagenta\\\\\\\":\\\\\\\"#6c71c4\\\\\\\",\\\\\\\"terminal.ansiBrightCyan\\\\\\\":\\\\\\\"#93a1a1\\\\\\\",\\\\\\\"terminal.ansiBrightWhite\\\\\\\":\\\\\\\"#eee8d5\\\\\\\",\\\\\\\"walkThrough.embeddedEditorBackground\\\\\\\":\\\\\\\"#00000014\\\\\\\"},\\\\\\\"watch\\\\\\\":false}\\\"},\\\"views.cachedViewPositions\\\":{\\\"version\\\":1,\\\"value\\\":\\\"[[\\\\\\\"workbench.panel.terminal\\\\\\\",{\\\\\\\"containerId\\\\\\\":\\\\\\\"workbench.panel.markers\\\\\\\"}],[\\\\\\\"workbench.panel.markers.view\\\\\\\",{\\\\\\\"containerId\\\\\\\":\\\\\\\"workbench.views.service.panel.0dcf4562-3bcc-4904-99f0-b9eeb1229380\\\\\\\"}],[\\\\\\\"workbench.panel.repl.view\\\\\\\",{\\\\\\\"containerId\\\\\\\":\\\\\\\"terminal\\\\\\\"}],[\\\\\\\"terminal\\\\\\\",{\\\\\\\"containerId\\\\\\\":\\\\\\\"workbench.views.service.panel.4ba08128-7799-4aa5-8459-7e6c4fd62c38\\\\\\\"}]]\\\"},\\\"views.cachedViewContainerLocations\\\":{\\\"version\\\":1,\\\"value\\\":\\\"[[\\\\\\\"workbench.views.service.panel.0dcf4562-3bcc-4904-99f0-b9eeb1229380\\\\\\\",1],[\\\\\\\"workbench.views.service.panel.4ba08128-7799-4aa5-8459-7e6c4fd62c38\\\\\\\",1]]\\\"},\\\"workbench.panel.repl.hidden\\\":{\\\"version\\\":1,\\\"value\\\":\\\"[{\\\\\\\"id\\\\\\\":\\\\\\\"workbench.panel.repl.view\\\\\\\",\\\\\\\"isHidden\\\\\\\":false}]\\\"},\\\"workbench.panel.markers.hidden\\\":{\\\"version\\\":1,\\\"value\\\":\\\"[{\\\\\\\"id\\\\\\\":\\\\\\\"workbench.panel.markers.view\\\\\\\",\\\\\\\"isHidden\\\\\\\":false},{\\\\\\\"id\\\\\\\":\\\\\\\"workbench.panel.terminal\\\\\\\",\\\\\\\"isHidden\\\\\\\":false,\\\\\\\"order\\\\\\\":0}]\\\"},\\\"workbench.panel.output.hidden\\\":{\\\"version\\\":1,\\\"value\\\":\\\"[{\\\\\\\"id\\\\\\\":\\\\\\\"workbench.panel.output\\\\\\\",\\\\\\\"isHidden\\\\\\\":false}]\\\"},\\\"terminal.hidden\\\":{\\\"version\\\":1,\\\"value\\\":\\\"[{\\\\\\\"id\\\\\\\":\\\\\\\"terminal\\\\\\\",\\\\\\\"isHidden\\\\\\\":false,\\\\\\\"order\\\\\\\":1},{\\\\\\\"id\\\\\\\":\\\\\\\"workbench.panel.repl.view\\\\\\\",\\\\\\\"isHidden\\\\\\\":false,\\\\\\\"order\\\\\\\":0}]\\\"},\\\"workbench.view.debug.state.hidden\\\":{\\\"version\\\":1,\\\"value\\\":\\\"[{\\\\\\\"id\\\\\\\":\\\\\\\"workbench.debug.variablesView\\\\\\\",\\\\\\\"isHidden\\\\\\\":false},{\\\\\\\"id\\\\\\\":\\\\\\\"workbench.debug.welcome\\\\\\\",\\\\\\\"isHidden\\\\\\\":false},{\\\\\\\"id\\\\\\\":\\\\\\\"workbench.debug.watchExpressionsView\\\\\\\",\\\\\\\"isHidden\\\\\\\":false},{\\\\\\\"id\\\\\\\":\\\\\\\"workbench.debug.callStackView\\\\\\\",\\\\\\\"isHidden\\\\\\\":false},{\\\\\\\"id\\\\\\\":\\\\\\\"workbench.debug.loadedScriptsView\\\\\\\",\\\\\\\"isHidden\\\\\\\":false},{\\\\\\\"id\\\\\\\":\\\\\\\"workbench.debug.breakPointsView\\\\\\\",\\\\\\\"isHidden\\\\\\\":false},{\\\\\\\"id\\\\\\\":\\\\\\\"jsBrowserBreakpoints\\\\\\\",\\\\\\\"isHidden\\\\\\\":false},{\\\\\\\"id\\\\\\\":\\\\\\\"extension.firefox.loadedScripts\\\\\\\",\\\\\\\"isHidden\\\\\\\":false}]\\\"},\\\"workbench.view.extensions.state.hidden\\\":{\\\"version\\\":1,\\\"value\\\":\\\"[{\\\\\\\"id\\\\\\\":\\\\\\\"extensions.enabledExtensionList\\\\\\\",\\\\\\\"isHidden\\\\\\\":false},{\\\\\\\"id\\\\\\\":\\\\\\\"extensions.popularExtensionsList\\\\\\\",\\\\\\\"isHidden\\\\\\\":false},{\\\\\\\"id\\\\\\\":\\\\\\\"extensions.enabledExtensionList2\\\\\\\",\\\\\\\"isHidden\\\\\\\":false},{\\\\\\\"id\\\\\\\":\\\\\\\"extensions.workspaceRecommendedList\\\\\\\",\\\\\\\"isHidden\\\\\\\":false},{\\\\\\\"id\\\\\\\":\\\\\\\"extensions.vscode-local.default\\\\\\\",\\\\\\\"isHidden\\\\\\\":false},{\\\\\\\"id\\\\\\\":\\\\\\\"extensions.recommendedList\\\\\\\",\\\\\\\"isHidden\\\\\\\":true},{\\\\\\\"id\\\\\\\":\\\\\\\"extensions.otherrecommendedList\\\\\\\",\\\\\\\"isHidden\\\\\\\":false},{\\\\\\\"id\\\\\\\":\\\\\\\"extensions.disabledExtensionList\\\\\\\",\\\\\\\"isHidden\\\\\\\":false},{\\\\\\\"id\\\\\\\":\\\\\\\"extensions.disabledExtensionList2\\\\\\\",\\\\\\\"isHidden\\\\\\\":false},{\\\\\\\"id\\\\\\\":\\\\\\\"extensions.listView\\\\\\\",\\\\\\\"isHidden\\\\\\\":false},{\\\\\\\"id\\\\\\\":\\\\\\\"extensions.builtInExtensionsList\\\\\\\",\\\\\\\"isHidden\\\\\\\":false},{\\\\\\\"id\\\\\\\":\\\\\\\"extensions.builtInBasicsExtensionsList\\\\\\\",\\\\\\\"isHidden\\\\\\\":false},{\\\\\\\"id\\\\\\\":\\\\\\\"extensions.builtInThemesExtensionsList\\\\\\\",\\\\\\\"isHidden\\\\\\\":false},{\\\\\\\"id\\\\\\\":\\\\\\\"extensions.vscode-local.installed\\\\\\\",\\\\\\\"isHidden\\\\\\\":false},{\\\\\\\"id\\\\\\\":\\\\\\\"extensions.vscode-local.outdated\\\\\\\",\\\\\\\"isHidden\\\\\\\":false},{\\\\\\\"id\\\\\\\":\\\\\\\"extensions.local.default\\\\\\\",\\\\\\\"isHidden\\\\\\\":false},{\\\\\\\"id\\\\\\\":\\\\\\\"extensions.local.installed\\\\\\\",\\\\\\\"isHidden\\\\\\\":false},{\\\\\\\"id\\\\\\\":\\\\\\\"extensions.local.outdated\\\\\\\",\\\\\\\"isHidden\\\\\\\":false},{\\\\\\\"id\\\\\\\":\\\\\\\"workbench.views.extensions.popular\\\\\\\",\\\\\\\"isHidden\\\\\\\":false},{\\\\\\\"id\\\\\\\":\\\\\\\"workbench.views.extensions.workspaceRecommendations\\\\\\\",\\\\\\\"isHidden\\\\\\\":false},{\\\\\\\"id\\\\\\\":\\\\\\\"workbench.views.extensions.installed\\\\\\\",\\\\\\\"isHidden\\\\\\\":false},{\\\\\\\"id\\\\\\\":\\\\\\\"workbench.views.extensions.otherRecommendations\\\\\\\",\\\\\\\"isHidden\\\\\\\":false},{\\\\\\\"id\\\\\\\":\\\\\\\"workbench.views.extensions.enabled\\\\\\\",\\\\\\\"isHidden\\\\\\\":true},{\\\\\\\"id\\\\\\\":\\\\\\\"workbench.views.extensions.disabled\\\\\\\",\\\\\\\"isHidden\\\\\\\":true},{\\\\\\\"id\\\\\\\":\\\\\\\"workbench.views.extensions.marketplace\\\\\\\",\\\\\\\"isHidden\\\\\\\":false},{\\\\\\\"id\\\\\\\":\\\\\\\"workbench.views.extensions.searchInstalled\\\\\\\",\\\\\\\"isHidden\\\\\\\":false},{\\\\\\\"id\\\\\\\":\\\\\\\"workbench.views.extensions.searchEnabled\\\\\\\",\\\\\\\"isHidden\\\\\\\":false},{\\\\\\\"id\\\\\\\":\\\\\\\"workbench.views.extensions.searchDisabled\\\\\\\",\\\\\\\"isHidden\\\\\\\":false},{\\\\\\\"id\\\\\\\":\\\\\\\"workbench.views.extensions.searchOutdated\\\\\\\",\\\\\\\"isHidden\\\\\\\":false},{\\\\\\\"id\\\\\\\":\\\\\\\"workbench.views.extensions.searchBuiltin\\\\\\\",\\\\\\\"isHidden\\\\\\\":false},{\\\\\\\"id\\\\\\\":\\\\\\\"workbench.views.extensions.builtinFeatureExtensions\\\\\\\",\\\\\\\"isHidden\\\\\\\":false},{\\\\\\\"id\\\\\\\":\\\\\\\"workbench.views.extensions.builtinThemeExtensions\\\\\\\",\\\\\\\"isHidden\\\\\\\":false},{\\\\\\\"id\\\\\\\":\\\\\\\"workbench.views.extensions.builtinProgrammingLanguageExtensions\\\\\\\",\\\\\\\"isHidden\\\\\\\":false},{\\\\\\\"id\\\\\\\":\\\\\\\"workbench.views.extensions.installed.empty\\\\\\\",\\\\\\\"isHidden\\\\\\\":false}]\\\"},\\\"workbench.explorer.views.state.hidden\\\":{\\\"version\\\":1,\\\"value\\\":\\\"[{\\\\\\\"id\\\\\\\":\\\\\\\"outline\\\\\\\",\\\\\\\"isHidden\\\\\\\":true},{\\\\\\\"id\\\\\\\":\\\\\\\"timeline\\\\\\\",\\\\\\\"isHidden\\\\\\\":false},{\\\\\\\"id\\\\\\\":\\\\\\\"workbench.explorer.openEditorsView\\\\\\\",\\\\\\\"isHidden\\\\\\\":false},{\\\\\\\"id\\\\\\\":\\\\\\\"workbench.explorer.emptyView\\\\\\\",\\\\\\\"isHidden\\\\\\\":false},{\\\\\\\"id\\\\\\\":\\\\\\\"workbench.explorer.fileView\\\\\\\",\\\\\\\"isHidden\\\\\\\":false},{\\\\\\\"id\\\\\\\":\\\\\\\"npm\\\\\\\",\\\\\\\"isHidden\\\\\\\":true},{\\\\\\\"id\\\\\\\":\\\\\\\"dartPackages\\\\\\\",\\\\\\\"isHidden\\\\\\\":true},{\\\\\\\"id\\\\\\\":\\\\\\\"commitViewProvider\\\\\\\",\\\\\\\"isHidden\\\\\\\":false},{\\\\\\\"id\\\\\\\":\\\\\\\"compareCommitViewProvider\\\\\\\",\\\\\\\"isHidden\\\\\\\":false},{\\\\\\\"id\\\\\\\":\\\\\\\"gitlens.views.repositories:explorer\\\\\\\",\\\\\\\"isHidden\\\\\\\":false},{\\\\\\\"id\\\\\\\":\\\\\\\"gitlens.views.fileHistory:explorer\\\\\\\",\\\\\\\"isHidden\\\\\\\":false},{\\\\\\\"id\\\\\\\":\\\\\\\"gitlens.views.lineHistory:explorer\\\\\\\",\\\\\\\"isHidden\\\\\\\":false},{\\\\\\\"id\\\\\\\":\\\\\\\"gitlens.views.compare:explorer\\\\\\\",\\\\\\\"isHidden\\\\\\\":false},{\\\\\\\"id\\\\\\\":\\\\\\\"gitlens.views.search:explorer\\\\\\\",\\\\\\\"isHidden\\\\\\\":false},{\\\\\\\"id\\\\\\\":\\\\\\\"todo-tree-view-explorer\\\\\\\",\\\\\\\"isHidden\\\\\\\":false},{\\\\\\\"id\\\\\\\":\\\\\\\"vscodeMarkdownNotesBacklinks\\\\\\\",\\\\\\\"isHidden\\\\\\\":true},{\\\\\\\"id\\\\\\\":\\\\\\\"cSpellRegExpView\\\\\\\",\\\\\\\"isHidden\\\\\\\":false},{\\\\\\\"id\\\\\\\":\\\\\\\"foam-vscode.tags-explorer\\\\\\\",\\\\\\\"isHidden\\\\\\\":false},{\\\\\\\"id\\\\\\\":\\\\\\\"dendronTreeView\\\\\\\",\\\\\\\"isHidden\\\\\\\":false},{\\\\\\\"id\\\\\\\":\\\\\\\"dendron.backlinksPanel\\\\\\\",\\\\\\\"isHidden\\\\\\\":false},{\\\\\\\"id\\\\\\\":\\\\\\\"foam-vscode.orphans\\\\\\\",\\\\\\\"isHidden\\\\\\\":false}]\\\"},\\\"workbench.scm.views.state.hidden\\\":{\\\"version\\\":1,\\\"value\\\":\\\"[{\\\\\\\"id\\\\\\\":\\\\\\\"workbench.scm\\\\\\\",\\\\\\\"isHidden\\\\\\\":false},{\\\\\\\"id\\\\\\\":\\\\\\\"scm.mainPane\\\\\\\",\\\\\\\"isHidden\\\\\\\":false},{\\\\\\\"id\\\\\\\":\\\\\\\"gitlens.views.repositories:scm\\\\\\\",\\\\\\\"isHidden\\\\\\\":false},{\\\\\\\"id\\\\\\\":\\\\\\\"gitlens.views.fileHistory:scm\\\\\\\",\\\\\\\"isHidden\\\\\\\":false},{\\\\\\\"id\\\\\\\":\\\\\\\"gitlens.views.lineHistory:scm\\\\\\\",\\\\\\\"isHidden\\\\\\\":false},{\\\\\\\"id\\\\\\\":\\\\\\\"gitlens.views.compare:scm\\\\\\\",\\\\\\\"isHidden\\\\\\\":false},{\\\\\\\"id\\\\\\\":\\\\\\\"gitlens.views.search:scm\\\\\\\",\\\\\\\"isHidden\\\\\\\":false},{\\\\\\\"id\\\\\\\":\\\\\\\"scm:repository:-1431201904\\\\\\\",\\\\\\\"isHidden\\\\\\\":false},{\\\\\\\"id\\\\\\\":\\\\\\\"scm:repository:-306308742\\\\\\\",\\\\\\\"isHidden\\\\\\\":false},{\\\\\\\"id\\\\\\\":\\\\\\\"scm:repository:1561878219\\\\\\\",\\\\\\\"isHidden\\\\\\\":false},{\\\\\\\"id\\\\\\\":\\\\\\\"scm:repository:1561882355\\\\\\\",\\\\\\\"isHidden\\\\\\\":false},{\\\\\\\"id\\\\\\\":\\\\\\\"scm:repository:1344178714\\\\\\\",\\\\\\\"isHidden\\\\\\\":false},{\\\\\\\"id\\\\\\\":\\\\\\\"scm:repository:1995166577\\\\\\\",\\\\\\\"isHidden\\\\\\\":false},{\\\\\\\"id\\\\\\\":\\\\\\\"scm:repository:-1666139056\\\\\\\",\\\\\\\"isHidden\\\\\\\":false},{\\\\\\\"id\\\\\\\":\\\\\\\"scm:repository:-641793485\\\\\\\",\\\\\\\"isHidden\\\\\\\":false},{\\\\\\\"id\\\\\\\":\\\\\\\"scm:repository:-1077107819\\\\\\\",\\\\\\\"isHidden\\\\\\\":false},{\\\\\\\"id\\\\\\\":\\\\\\\"scm:repository:-1498731746\\\\\\\",\\\\\\\"isHidden\\\\\\\":true},{\\\\\\\"id\\\\\\\":\\\\\\\"scm:repository:-1886454445\\\\\\\",\\\\\\\"isHidden\\\\\\\":false},{\\\\\\\"id\\\\\\\":\\\\\\\"scm:repository:1418782548\\\\\\\",\\\\\\\"isHidden\\\\\\\":false},{\\\\\\\"id\\\\\\\":\\\\\\\"scm:repository:-863557518\\\\\\\",\\\\\\\"isHidden\\\\\\\":false},{\\\\\\\"id\\\\\\\":\\\\\\\"scm:repository:1486862839\\\\\\\",\\\\\\\"isHidden\\\\\\\":false},{\\\\\\\"id\\\\\\\":\\\\\\\"scm:repository:1234930056\\\\\\\",\\\\\\\"isHidden\\\\\\\":false},{\\\\\\\"id\\\\\\\":\\\\\\\"scm:repository:-1678449748\\\\\\\",\\\\\\\"isHidden\\\\\\\":false},{\\\\\\\"id\\\\\\\":\\\\\\\"scm:repository:-219302696\\\\\\\",\\\\\\\"isHidden\\\\\\\":false},{\\\\\\\"id\\\\\\\":\\\\\\\"scm:repository:-218687191\\\\\\\",\\\\\\\"isHidden\\\\\\\":false},{\\\\\\\"id\\\\\\\":\\\\\\\"scm:repository:-542074605\\\\\\\",\\\\\\\"isHidden\\\\\\\":false},{\\\\\\\"id\\\\\\\":\\\\\\\"scm:repository:111497548\\\\\\\",\\\\\\\"isHidden\\\\\\\":false},{\\\\\\\"id\\\\\\\":\\\\\\\"scm:repository:954114005\\\\\\\",\\\\\\\"isHidden\\\\\\\":false},{\\\\\\\"id\\\\\\\":\\\\\\\"scm:repository:941694030\\\\\\\",\\\\\\\"isHidden\\\\\\\":false},{\\\\\\\"id\\\\\\\":\\\\\\\"scm:repository:1695073159\\\\\\\",\\\\\\\"isHidden\\\\\\\":false},{\\\\\\\"id\\\\\\\":\\\\\\\"scm:repository:803422450\\\\\\\",\\\\\\\"isHidden\\\\\\\":false},{\\\\\\\"id\\\\\\\":\\\\\\\"scm:repository:1599669516\\\\\\\",\\\\\\\"isHidden\\\\\\\":false},{\\\\\\\"id\\\\\\\":\\\\\\\"scm:repository:-93880081\\\\\\\",\\\\\\\"isHidden\\\\\\\":false},{\\\\\\\"id\\\\\\\":\\\\\\\"scm:repository:1031013081\\\\\\\",\\\\\\\"isHidden\\\\\\\":false},{\\\\\\\"id\\\\\\\":\\\\\\\"scm:repository:1599673652\\\\\\\",\\\\\\\"isHidden\\\\\\\":false},{\\\\\\\"id\\\\\\\":\\\\\\\"scm:repository:348519161\\\\\\\",\\\\\\\"isHidden\\\\\\\":false},{\\\\\\\"id\\\\\\\":\\\\\\\"scm:repository:-962478896\\\\\\\",\\\\\\\"isHidden\\\\\\\":false},{\\\\\\\"id\\\\\\\":\\\\\\\"scm:repository:744950855\\\\\\\",\\\\\\\"isHidden\\\\\\\":false},{\\\\\\\"id\\\\\\\":\\\\\\\"scm:repository:-152087532\\\\\\\",\\\\\\\"isHidden\\\\\\\":false},{\\\\\\\"id\\\\\\\":\\\\\\\"scm:repository:138731558\\\\\\\",\\\\\\\"isHidden\\\\\\\":false},{\\\\\\\"id\\\\\\\":\\\\\\\"scm:repository:1653395186\\\\\\\",\\\\\\\"isHidden\\\\\\\":false},{\\\\\\\"id\\\\\\\":\\\\\\\"scm:repository:1438809706\\\\\\\",\\\\\\\"isHidden\\\\\\\":false},{\\\\\\\"id\\\\\\\":\\\\\\\"scm:repository:1653560354\\\\\\\",\\\\\\\"isHidden\\\\\\\":false},{\\\\\\\"id\\\\\\\":\\\\\\\"scm:repository:2042984806\\\\\\\",\\\\\\\"isHidden\\\\\\\":false},{\\\\\\\"id\\\\\\\":\\\\\\\"scm:repository:1726587514\\\\\\\",\\\\\\\"isHidden\\\\\\\":false},{\\\\\\\"id\\\\\\\":\\\\\\\"scm:repository:605890851\\\\\\\",\\\\\\\"isHidden\\\\\\\":false},{\\\\\\\"id\\\\\\\":\\\\\\\"workbench.scm.repositories\\\\\\\",\\\\\\\"isHidden\\\\\\\":true},{\\\\\\\"id\\\\\\\":\\\\\\\"gitlens.views.repositories\\\\\\\",\\\\\\\"isHidden\\\\\\\":false},{\\\\\\\"id\\\\\\\":\\\\\\\"gitlens.views.commits\\\\\\\",\\\\\\\"isHidden\\\\\\\":false},{\\\\\\\"id\\\\\\\":\\\\\\\"gitlens.views.fileHistory\\\\\\\",\\\\\\\"isHidden\\\\\\\":false},{\\\\\\\"id\\\\\\\":\\\\\\\"gitlens.views.lineHistory\\\\\\\",\\\\\\\"isHidden\\\\\\\":true},{\\\\\\\"id\\\\\\\":\\\\\\\"gitlens.views.branches\\\\\\\",\\\\\\\"isHidden\\\\\\\":false},{\\\\\\\"id\\\\\\\":\\\\\\\"gitlens.views.remotes\\\\\\\",\\\\\\\"isHidden\\\\\\\":false},{\\\\\\\"id\\\\\\\":\\\\\\\"gitlens.views.stashes\\\\\\\",\\\\\\\"isHidden\\\\\\\":false},{\\\\\\\"id\\\\\\\":\\\\\\\"gitlens.views.tags\\\\\\\",\\\\\\\"isHidden\\\\\\\":false},{\\\\\\\"id\\\\\\\":\\\\\\\"gitlens.views.contributors\\\\\\\",\\\\\\\"isHidden\\\\\\\":true},{\\\\\\\"id\\\\\\\":\\\\\\\"gitlens.views.searchAndCompare\\\\\\\",\\\\\\\"isHidden\\\\\\\":true}]\\\"},\\\"workbench.view.search.state.hidden\\\":{\\\"version\\\":1,\\\"value\\\":\\\"[{\\\\\\\"id\\\\\\\":\\\\\\\"workbench.view.search\\\\\\\",\\\\\\\"isHidden\\\\\\\":false}]\\\"},\\\"workbench.panel.pinnedPanels\\\":{\\\"version\\\":1,\\\"value\\\":\\\"[{\\\\\\\"id\\\\\\\":\\\\\\\"workbench.views.service.panel.0dcf4562-3bcc-4904-99f0-b9eeb1229380\\\\\\\",\\\\\\\"name\\\\\\\":\\\\\\\"Problems\\\\\\\",\\\\\\\"pinned\\\\\\\":true,\\\\\\\"visible\\\\\\\":true},{\\\\\\\"id\\\\\\\":\\\\\\\"terminal\\\\\\\",\\\\\\\"name\\\\\\\":\\\\\\\"Debug Console\\\\\\\",\\\\\\\"pinned\\\\\\\":true,\\\\\\\"order\\\\\\\":3,\\\\\\\"visible\\\\\\\":true},{\\\\\\\"id\\\\\\\":\\\\\\\"workbench.panel.markers\\\\\\\",\\\\\\\"name\\\\\\\":\\\\\\\"Problems\\\\\\\",\\\\\\\"pinned\\\\\\\":true,\\\\\\\"order\\\\\\\":0,\\\\\\\"visible\\\\\\\":false},{\\\\\\\"id\\\\\\\":\\\\\\\"workbench.panel.repl\\\\\\\",\\\\\\\"name\\\\\\\":\\\\\\\"Debug Console\\\\\\\",\\\\\\\"pinned\\\\\\\":true,\\\\\\\"order\\\\\\\":2,\\\\\\\"visible\\\\\\\":false},{\\\\\\\"id\\\\\\\":\\\\\\\"workbench.panel.output\\\\\\\",\\\\\\\"name\\\\\\\":\\\\\\\"Output\\\\\\\",\\\\\\\"pinned\\\\\\\":true,\\\\\\\"order\\\\\\\":1,\\\\\\\"visible\\\\\\\":true},{\\\\\\\"id\\\\\\\":\\\\\\\"refactorPreview\\\\\\\",\\\\\\\"name\\\\\\\":\\\\\\\"Refactor Preview\\\\\\\",\\\\\\\"pinned\\\\\\\":true,\\\\\\\"visible\\\\\\\":false},{\\\\\\\"id\\\\\\\":\\\\\\\"workbench.views.service.panel.4ba08128-7799-4aa5-8459-7e6c4fd62c38\\\\\\\",\\\\\\\"name\\\\\\\":\\\\\\\"Terminal\\\\\\\",\\\\\\\"pinned\\\\\\\":true,\\\\\\\"visible\\\\\\\":true}]\\\"},\\\"workbench.views.service.panel.0dcf4562-3bcc-4904-99f0-b9eeb1229380.state.hidden\\\":{\\\"version\\\":1,\\\"value\\\":\\\"[{\\\\\\\"id\\\\\\\":\\\\\\\"workbench.panel.markers.view\\\\\\\",\\\\\\\"isHidden\\\\\\\":false}]\\\"},\\\"workbench.activity.pinnedViewlets2\\\":{\\\"version\\\":1,\\\"value\\\":\\\"[{\\\\\\\"id\\\\\\\":\\\\\\\"workbench.view.explorer\\\\\\\",\\\\\\\"pinned\\\\\\\":true,\\\\\\\"visible\\\\\\\":true,\\\\\\\"order\\\\\\\":0},{\\\\\\\"id\\\\\\\":\\\\\\\"workbench.view.search\\\\\\\",\\\\\\\"pinned\\\\\\\":true,\\\\\\\"visible\\\\\\\":true,\\\\\\\"order\\\\\\\":1},{\\\\\\\"id\\\\\\\":\\\\\\\"workbench.view.extension.references-view\\\\\\\",\\\\\\\"pinned\\\\\\\":true,\\\\\\\"visible\\\\\\\":false,\\\\\\\"order\\\\\\\":7},{\\\\\\\"id\\\\\\\":\\\\\\\"workbench.view.scm\\\\\\\",\\\\\\\"pinned\\\\\\\":true,\\\\\\\"visible\\\\\\\":true,\\\\\\\"order\\\\\\\":2},{\\\\\\\"id\\\\\\\":\\\\\\\"workbench.view.extension.gitlens\\\\\\\",\\\\\\\"pinned\\\\\\\":true,\\\\\\\"visible\\\\\\\":false,\\\\\\\"order\\\\\\\":10},{\\\\\\\"id\\\\\\\":\\\\\\\"workbench.view.debug\\\\\\\",\\\\\\\"pinned\\\\\\\":true,\\\\\\\"visible\\\\\\\":true,\\\\\\\"order\\\\\\\":2},{\\\\\\\"id\\\\\\\":\\\\\\\"workbench.view.remote\\\\\\\",\\\\\\\"pinned\\\\\\\":true,\\\\\\\"visible\\\\\\\":false,\\\\\\\"order\\\\\\\":4},{\\\\\\\"id\\\\\\\":\\\\\\\"workbench.view.extension.test\\\\\\\",\\\\\\\"pinned\\\\\\\":true,\\\\\\\"visible\\\\\\\":true,\\\\\\\"order\\\\\\\":6},{\\\\\\\"id\\\\\\\":\\\\\\\"workbench.view.extension.github-pull-requests\\\\\\\",\\\\\\\"pinned\\\\\\\":true,\\\\\\\"visible\\\\\\\":true,\\\\\\\"order\\\\\\\":8},{\\\\\\\"id\\\\\\\":\\\\\\\"workbench.view.extension.todo-tree-container\\\\\\\",\\\\\\\"pinned\\\\\\\":true,\\\\\\\"visible\\\\\\\":false,\\\\\\\"order\\\\\\\":10},{\\\\\\\"id\\\\\\\":\\\\\\\"workbench.view.extension.flutter\\\\\\\",\\\\\\\"pinned\\\\\\\":true,\\\\\\\"visible\\\\\\\":false,\\\\\\\"order\\\\\\\":9},{\\\\\\\"id\\\\\\\":\\\\\\\"workbench.view.extensions\\\\\\\",\\\\\\\"pinned\\\\\\\":true,\\\\\\\"visible\\\\\\\":true,\\\\\\\"order\\\\\\\":4},{\\\\\\\"id\\\\\\\":\\\\\\\"workbench.view.extension.cspell-explorer\\\\\\\",\\\\\\\"pinned\\\\\\\":true,\\\\\\\"visible\\\\\\\":false,\\\\\\\"order\\\\\\\":11},{\\\\\\\"id\\\\\\\":\\\\\\\"workbench.view.sync\\\\\\\",\\\\\\\"pinned\\\\\\\":true,\\\\\\\"visible\\\\\\\":false}]\\\"},\\\"workbench.statusbar.hidden\\\":{\\\"version\\\":1,\\\"value\\\":\\\"[\\\\\\\"streetsidesoftware.code-spell-checker\\\\\\\",\\\\\\\"AzMoza.aqueduct-helper\\\\\\\",\\\\\\\"eamodio.gitlens\\\\\\\",\\\\\\\"status.editor.selection\\\\\\\",\\\\\\\"status.editor.indentation\\\\\\\",\\\\\\\"golang.go\\\\\\\"]\\\"},\\\"extensionsAssistant/importantRecommendationsIgnore\\\":{\\\"version\\\":1,\\\"value\\\":\\\"[\\\\\\\"ms-azuretools.vscode-docker\\\\\\\",\\\\\\\"ms-vscode-remote.remote-containers\\\\\\\"]\\\"},\\\"workbench.view.extension.test.state.hidden\\\":{\\\"version\\\":1,\\\"value\\\":\\\"[{\\\\\\\"id\\\\\\\":\\\\\\\"dartTestTree\\\\\\\",\\\\\\\"isHidden\\\\\\\":false},{\\\\\\\"id\\\\\\\":\\\\\\\"python_tests\\\\\\\",\\\\\\\"isHidden\\\\\\\":false},{\\\\\\\"id\\\\\\\":\\\\\\\"workbench.view.testing\\\\\\\",\\\\\\\"isHidden\\\\\\\":false}]\\\"},\\\"nps/sessionCount\\\":{\\\"version\\\":1,\\\"value\\\":\\\"9\\\"},\\\"nps/lastSessionDate\\\":{\\\"version\\\":1,\\\"value\\\":\\\"Mon Jun 15 2020\\\"},\\\"nps/skipVersion\\\":{\\\"version\\\":1,\\\"value\\\":\\\"1.46.0\\\"},\\\"nps/isCandidate\\\":{\\\"version\\\":1,\\\"value\\\":\\\"false\\\"},\\\"cpp.1.sessionCount\\\":{\\\"version\\\":1,\\\"value\\\":\\\"164\\\"},\\\"cpp.1.lastSessionDate\\\":{\\\"version\\\":1,\\\"value\\\":\\\"Wed Feb 17 2021\\\"},\\\"java.2.sessionCount\\\":{\\\"version\\\":1,\\\"value\\\":\\\"164\\\"},\\\"java.2.lastSessionDate\\\":{\\\"version\\\":1,\\\"value\\\":\\\"Wed Feb 17 2021\\\"},\\\"java.2.editedCount\\\":{\\\"version\\\":1,\\\"value\\\":\\\"4\\\"},\\\"java.2.editedDate\\\":{\\\"version\\\":1,\\\"value\\\":\\\"Tue Jan 26 2021\\\"},\\\"javascript.1.sessionCount\\\":{\\\"version\\\":1,\\\"value\\\":\\\"164\\\"},\\\"javascript.1.lastSessionDate\\\":{\\\"version\\\":1,\\\"value\\\":\\\"Wed Feb 17 2021\\\"},\\\"javascript.1.editedCount\\\":{\\\"version\\\":1,\\\"value\\\":\\\"2\\\"},\\\"javascript.1.editedDate\\\":{\\\"version\\\":1,\\\"value\\\":\\\"Tue Nov 24 2020\\\"},\\\"typescript.1.sessionCount\\\":{\\\"version\\\":1,\\\"value\\\":\\\"164\\\"},\\\"typescript.1.lastSessionDate\\\":{\\\"version\\\":1,\\\"value\\\":\\\"Wed Feb 17 2021\\\"},\\\"workbench.view.extension.references-view.state.hidden\\\":{\\\"version\\\":1,\\\"value\\\":\\\"[{\\\\\\\"id\\\\\\\":\\\\\\\"references-view.tree\\\\\\\",\\\\\\\"isHidden\\\\\\\":false},{\\\\\\\"id\\\\\\\":\\\\\\\"CppReferencesView\\\\\\\",\\\\\\\"isHidden\\\\\\\":false}]\\\"},\\\"workbench.view.extension.flutter.state.hidden\\\":{\\\"version\\\":1,\\\"value\\\":\\\"[{\\\\\\\"id\\\\\\\":\\\\\\\"dartFlutterOutline\\\\\\\",\\\\\\\"isHidden\\\\\\\":false}]\\\"},\\\"workbench.view.extension.gitlens.state.hidden\\\":{\\\"version\\\":1,\\\"value\\\":\\\"[{\\\\\\\"id\\\\\\\":\\\\\\\"gitlens.views.repositories:gitlens\\\\\\\",\\\\\\\"isHidden\\\\\\\":false},{\\\\\\\"id\\\\\\\":\\\\\\\"gitlens.views.fileHistory:gitlens\\\\\\\",\\\\\\\"isHidden\\\\\\\":false},{\\\\\\\"id\\\\\\\":\\\\\\\"gitlens.views.lineHistory:gitlens\\\\\\\",\\\\\\\"isHidden\\\\\\\":false},{\\\\\\\"id\\\\\\\":\\\\\\\"gitlens.views.compare:gitlens\\\\\\\",\\\\\\\"isHidden\\\\\\\":false},{\\\\\\\"id\\\\\\\":\\\\\\\"gitlens.views.search:gitlens\\\\\\\",\\\\\\\"isHidden\\\\\\\":false},{\\\\\\\"id\\\\\\\":\\\\\\\"gitlens.views.updates\\\\\\\",\\\\\\\"isHidden\\\\\\\":false},{\\\\\\\"id\\\\\\\":\\\\\\\"gitlens.views.welcome\\\\\\\",\\\\\\\"isHidden\\\\\\\":false}]\\\"},\\\"workbench.view.extension.todo-tree-container.state.hidden\\\":{\\\"version\\\":1,\\\"value\\\":\\\"[{\\\\\\\"id\\\\\\\":\\\\\\\"todo-tree-view\\\\\\\",\\\\\\\"isHidden\\\\\\\":false}]\\\"},\\\"workbench.telemetryOptOutShown\\\":{\\\"version\\\":1,\\\"value\\\":\\\"true\\\"},\\\"hasNotifiedOfSettingsAutosave\\\":{\\\"version\\\":1,\\\"value\\\":\\\"true\\\"},\\\"commandPalette.mru.cache\\\":{\\\"version\\\":1,\\\"value\\\":\\\"{\\\\\\\"usesLRU\\\\\\\":true,\\\\\\\"entries\\\\\\\":[{\\\\\\\"key\\\\\\\":\\\\\\\"extension.markdown-pdf.pdf\\\\\\\",\\\\\\\"value\\\\\\\":460},{\\\\\\\"key\\\\\\\":\\\\\\\"git.viewLineHistory\\\\\\\",\\\\\\\"value\\\\\\\":463},{\\\\\\\"key\\\\\\\":\\\\\\\"workbench.extensions.action.showEnabledExtensions\\\\\\\",\\\\\\\"value\\\\\\\":595},{\\\\\\\"key\\\\\\\":\\\\\\\"search.action.expandSearchResults\\\\\\\",\\\\\\\"value\\\\\\\":674},{\\\\\\\"key\\\\\\\":\\\\\\\"search.action.collapseSearchResults\\\\\\\",\\\\\\\"value\\\\\\\":713},{\\\\\\\"key\\\\\\\":\\\\\\\"dart.runAllTestsWithoutDebugging\\\\\\\",\\\\\\\"value\\\\\\\":716},{\\\\\\\"key\\\\\\\":\\\\\\\"git.commit.compare\\\\\\\",\\\\\\\"value\\\\\\\":740},{\\\\\\\"key\\\\\\\":\\\\\\\"extension.pasteImage\\\\\\\",\\\\\\\"value\\\\\\\":872},{\\\\\\\"key\\\\\\\":\\\\\\\"editor.action.formatDocument\\\\\\\",\\\\\\\"value\\\\\\\":888},{\\\\\\\"key\\\\\\\":\\\\\\\"editor.action.formatDocument.multiple\\\\\\\",\\\\\\\"value\\\\\\\":894},{\\\\\\\"key\\\\\\\":\\\\\\\"flutter.packages.upgrade\\\\\\\",\\\\\\\"value\\\\\\\":917},{\\\\\\\"key\\\\\\\":\\\\\\\"workbench.userDataSync.actions.settings\\\\\\\",\\\\\\\"value\\\\\\\":1006},{\\\\\\\"key\\\\\\\":\\\\\\\"editor.action.insertCursorAtEndOfEachLineSelected\\\\\\\",\\\\\\\"value\\\\\\\":1011},{\\\\\\\"key\\\\\\\":\\\\\\\"workbench.action.debug.configure\\\\\\\",\\\\\\\"value\\\\\\\":1092},{\\\\\\\"key\\\\\\\":\\\\\\\"dart.openDevTools\\\\\\\",\\\\\\\"value\\\\\\\":1123},{\\\\\\\"key\\\\\\\":\\\\\\\"editor.action.measureExtHostLatency\\\\\\\",\\\\\\\"value\\\\\\\":1132},{\\\\\\\"key\\\\\\\":\\\\\\\"flutter.createProject.package\\\\\\\",\\\\\\\"value\\\\\\\":1229},{\\\\\\\"key\\\\\\\":\\\\\\\"workbench.action.toggleZenMode\\\\\\\",\\\\\\\"value\\\\\\\":1269},{\\\\\\\"key\\\\\\\":\\\\\\\"dendron.initWS\\\\\\\",\\\\\\\"value\\\\\\\":1281},{\\\\\\\"key\\\\\\\":\\\\\\\"editor.action.insertSnippet\\\\\\\",\\\\\\\"value\\\\\\\":1286},{\\\\\\\"key\\\\\\\":\\\\\\\"dendron.createGlobalSnippet\\\\\\\",\\\\\\\"value\\\\\\\":1287},{\\\\\\\"key\\\\\\\":\\\\\\\"dendron.gotoGlobalSnippet\\\\\\\",\\\\\\\"value\\\\\\\":1290},{\\\\\\\"key\\\\\\\":\\\\\\\"workbench.action.openGlobalSettings\\\\\\\",\\\\\\\"value\\\\\\\":1292},{\\\\\\\"key\\\\\\\":\\\\\\\"dendron.showNoteGraph\\\\\\\",\\\\\\\"value\\\\\\\":1295},{\\\\\\\"key\\\\\\\":\\\\\\\"dendron.showSchemaGraph\\\\\\\",\\\\\\\"value\\\\\\\":1296},{\\\\\\\"key\\\\\\\":\\\\\\\"dendron.deleteNode\\\\\\\",\\\\\\\"value\\\\\\\":1300},{\\\\\\\"key\\\\\\\":\\\\\\\"dendron.syncNoteGraph\\\\\\\",\\\\\\\"value\\\\\\\":1302},{\\\\\\\"key\\\\\\\":\\\\\\\"dendron.renameNote\\\\\\\",\\\\\\\"value\\\\\\\":1349},{\\\\\\\"key\\\\\\\":\\\\\\\"workbench.action.installCommandLine\\\\\\\",\\\\\\\"value\\\\\\\":1412},{\\\\\\\"key\\\\\\\":\\\\\\\"dart.startLogging\\\\\\\",\\\\\\\"value\\\\\\\":1433},{\\\\\\\"key\\\\\\\":\\\\\\\"perfview.show\\\\\\\",\\\\\\\"value\\\\\\\":1437},{\\\\\\\"key\\\\\\\":\\\\\\\"workbench.action.reloadWindowWithExtensionsDisabled\\\\\\\",\\\\\\\"value\\\\\\\":1445},{\\\\\\\"key\\\\\\\":\\\\\\\"dart.openExtensionLog\\\\\\\",\\\\\\\"value\\\\\\\":1446},{\\\\\\\"key\\\\\\\":\\\\\\\"workbench.action.showRuntimeExtensions\\\\\\\",\\\\\\\"value\\\\\\\":1447},{\\\\\\\"key\\\\\\\":\\\\\\\"pubspec-assist.addDevDependency\\\\\\\",\\\\\\\"value\\\\\\\":1484},{\\\\\\\"key\\\\\\\":\\\\\\\"flutter.createProject\\\\\\\",\\\\\\\"value\\\\\\\":1548},{\\\\\\\"key\\\\\\\":\\\\\\\"pubspec-assist.sortAllDependencies\\\\\\\",\\\\\\\"value\\\\\\\":1648},{\\\\\\\"key\\\\\\\":\\\\\\\"workbench.action.toggleCenteredLayout\\\\\\\",\\\\\\\"value\\\\\\\":1665},{\\\\\\\"key\\\\\\\":\\\\\\\"foam-vscode.open-daily-note\\\\\\\",\\\\\\\"value\\\\\\\":1666},{\\\\\\\"key\\\\\\\":\\\\\\\"markdown.showPreviewToSide\\\\\\\",\\\\\\\"value\\\\\\\":1667},{\\\\\\\"key\\\\\\\":\\\\\\\"foam-vscode.tags-explorer.focus\\\\\\\",\\\\\\\"value\\\\\\\":1668},{\\\\\\\"key\\\\\\\":\\\\\\\"foam-vscode.create-note-from-template\\\\\\\",\\\\\\\"value\\\\\\\":1669},{\\\\\\\"key\\\\\\\":\\\\\\\"workbench.files.action.collapseExplorerFolders\\\\\\\",\\\\\\\"value\\\\\\\":1680},{\\\\\\\"key\\\\\\\":\\\\\\\"workbench.action.reloadWindow\\\\\\\",\\\\\\\"value\\\\\\\":1682},{\\\\\\\"key\\\\\\\":\\\\\\\"pubspec-assist.addDependency\\\\\\\",\\\\\\\"value\\\\\\\":1684},{\\\\\\\"key\\\\\\\":\\\\\\\"dart.createProject\\\\\\\",\\\\\\\"value\\\\\\\":1686},{\\\\\\\"key\\\\\\\":\\\\\\\"workbench.action.openRecent\\\\\\\",\\\\\\\"value\\\\\\\":1690},{\\\\\\\"key\\\\\\\":\\\\\\\"flutter.selectDevice\\\\\\\",\\\\\\\"value\\\\\\\":1693},{\\\\\\\"key\\\\\\\":\\\\\\\"gitlens.toggleLineBlame\\\\\\\",\\\\\\\"value\\\\\\\":1695},{\\\\\\\"key\\\\\\\":\\\\\\\"workbench.action.openSettingsJson\\\\\\\",\\\\\\\"value\\\\\\\":1696}]}\\\"},\\\"commandPalette.mru.counter\\\":{\\\"version\\\":1,\\\"value\\\":\\\"1697\\\"},\\\"terminal.integrated.showTerminalConfigPrompt\\\":{\\\"version\\\":1,\\\"value\\\":\\\"false\\\"},\\\"scm/input:Git:/Users/chris/Coding/hokaido/pumpkins\\\":{\\\"version\\\":1,\\\"value\\\":\\\"[\\\\\\\"load one book at a time and trash old entries on select book\\\\\\\",\\\\\\\"nullfix\\\\\\\",\\\\\\\"nextFlashcard no longer triggers on setActiveBook\\\\\\\",\\\\\\\"on insert to sentence when synonyms are present, allow choice\\\\\\\",\\\\\\\"clone/copyFrom for Options (flashcard decks)\\\\\\\",\\\\\\\"autofocus field\\\\\\\",\\\\\\\"refactor entry dialog with private variables\\\\\\\",\\\\\\\"epub reader remembers position\\\\\\\",\\\\\\\"readerStore per book + remember last contentId\\\\\\\",\\\\\\\"check isPhrase in hasChanged\\\\\\\",\\\\\\\"rename drawertiles\\\\\\\",\\\\\\\"revamped EntrySelectionView\\\\\\\",\\\\\\\"batch convert words/phrases\\\\\\\",\\\\\\\"\\\\\\\",\\\\\\\"batch convert words/phrases\\\\\\\",\\\\\\\"\\\\\\\\\\\\\\\"Experimental feature\\\\\\\\\\\\\\\" label on epub\\\\\\\",\\\\\\\"updated text\\\\\\\",\\\\\\\"created automatically set bookId to active if none given\\\\\\\",\\\\\\\"helpButton hidden in popupmenu reader\\\\\\\",\\\\\\\"set mostRecentReaderContentId on save new one\\\\\\\",\\\\\\\"set enableJS from sharedprefs\\\\\\\",\\\\\\\"revamped LookUpWebsites with three types: targetToSource, sourceToTarget or bothDirections\\\\\\\",\\\\\\\"modified sort was inverted fix\\\\\\\",\\\\\\\"undo flashcard now tolerates trashed/suspended words\\\\\\\",\\\\\\\"cleaning\\\\\\\",\\\\\\\"showNote/Tags for flashcards\\\\\\\",\\\\\\\"database version in about\\\\\\\",\\\\\\\"bumped to 0.0.2\\\\\\\",\\\\\\\"cleaning\\\\\\\",\\\\\\\"flashcards nextWord called on loadEntries\\\\\\\",\\\\\\\"same hight appbars flashcardview\\\\\\\",\\\\\\\"\\\\\\\",\\\\\\\"same hight appbars flashcardview\\\\\\\",\\\\\\\"lookupwebsitedialog fixes, hasChanged, WillPop etc.\\\\\\\",\\\\\\\"advSearchStore per book\\\\\\\",\\\\\\\"ignoreDiacritics per book\\\\\\\",\\\\\\\"set correct index on add lookupwebsite\\\\\\\",\\\\\\\"onSelectionChange on selectabletext on master\\\\\\\",\\\\\\\"no more using copy to lookup\\\\\\\",\\\\\\\"refactor\\\\\\\",\\\\\\\"basic duplicate checker for single duplicates in EntryDialog and ReaderView\\\\\\\",\\\\\\\"bugfix: after first added phrase entrydialog would switch to word\\\\\\\",\\\\\\\"copybutton reader mode\\\\\\\",\\\\\\\"autofocus readercontentdialog\\\\\\\",\\\\\\\"Slovak to English -> From Slovak\\\\\\\",\\\\\\\"bigger hitbox dismissKeyboardButton\\\\\\\",\\\\\\\"bumped version\\\\\\\",\\\\\\\"\\\\\\\",\\\\\\\"bumped version\\\\\\\",\\\\\\\"\\\\\\\"]\\\"},\\\"scm/input:Git:/Users/chris/Coding/flutter\\\":{\\\"version\\\":1,\\\"value\\\":\\\"[\\\\\\\"\\\\\\\"]\\\"},\\\"scm/input:Git:/Users/chris/Coding/bioservo/ironconnectpro\\\":{\\\"version\\\":1,\\\"value\\\":\\\"[\\\\\\\"refactor sort button\\\\\\\",\\\\\\\"bugfix: datetime modified was compared to created on sort\\\\\\\",\\\\\\\"renamed GenericTile to BioExpansionTile\\\\\\\",\\\\\\\"\\\\\\\",\\\\\\\"renamed GenericTile to BioExpansionTile\\\\\\\",\\\\\\\"onExpand, scroll to fit entire widget\\\\\\\",\\\\\\\"on select company, show StackedRefreshIndicator\\\\\\\",\\\\\\\"indent drawer tiles for single instalation too\\\\\\\",\\\\\\\"refactor\\\\\\\",\\\\\\\"Enable analyses for  installations from companies tab\\\\\\\",\\\\\\\"refactor of ObservableFuture on fetch method\\\\\\\",\\\\\\\"Big refactor of PopupMenu\\\\\\\",\\\\\\\"exceptionAlert method for handling BiocloudErrors\\\\\\\",\\\\\\\"navigator.push replaced by utility push(context, child) method\\\\\\\",\\\\\\\"\\\\\\\",\\\\\\\"navigator.push replaced by utility push(context, child) method\\\\\\\",\\\\\\\"refactor: more usage of showD() and pop() utility methods\\\\\\\",\\\\\\\"renamed notif() to toast()\\\\\\\",\\\\\\\"null check fix\\\\\\\",\\\\\\\"padding fixes\\\\\\\",\\\\\\\"Better error-handling if no internet\\\\\\\",\\\\\\\"listtile in appbar for device management/data analysis\\\\\\\",\\\\\\\"\\\\\\\",\\\\\\\"listtile in appbar for device management/data analysis\\\\\\\",\\\\\\\"bugfix: analyses didn't fetch on change installation\\\\\\\",\\\\\\\"refactor, reversed delete button placement in alert dialog\\\\\\\",\\\\\\\"more stylish textfield for entering into log\\\\\\\",\\\\\\\"removed redundant Flexible widget\\\\\\\",\\\\\\\"cleaning up todos\\\\\\\",\\\\\\\"toast on notched iPhones now has proper padding\\\\\\\",\\\\\\\"bumped version\\\\\\\",\\\\\\\"switched to git dependency\\\\\\\",\\\\\\\"added parameter to avoid encryption dialog on uploading to appstoreconnect\\\\\\\",\\\\\\\"upgraded yaml\\\\\\\",\\\\\\\"./build.sh and updated pubspec\\\\\\\",\\\\\\\"cleaning\\\\\\\",\\\\\\\"UserDialog uses new API for changing customer\\\\\\\",\\\\\\\"alert on incorrect permissions\\\\\\\",\\\\\\\"renaming\\\\\\\",\\\\\\\"refactor\\\\\\\",\\\\\\\"copy email to clipboard onEdit account\\\\\\\",\\\\\\\"clear secure_storage on startup if previously logged in to test server\\\\\\\",\\\\\\\"Refactor, renaming\\\\\\\",\\\\\\\"big refactor to bioflutterlib\\\\\\\",\\\\\\\"more refactor to bioflutterlib\\\\\\\",\\\\\\\"renaming and refactor to bioflutterlib\\\\\\\",\\\\\\\"import fix\\\\\\\",\\\\\\\"merge fixes\\\\\\\",\\\\\\\"removed intl packages that we don't use\\\\\\\",\\\\\\\"\\\\\\\"]\\\"},\\\"scm/input:Git:/Users/chris/Coding/bioservo/biocloudlib\\\":{\\\"version\\\":1,\\\"value\\\":\\\"[\\\\\\\"added customer variable to user class\\\\\\\",\\\\\\\"remove toJsonWithoutId in favour of toJson()..remove(\\\\\\\\\\\\\\\"id\\\\\\\\\\\\\\\")\\\\\\\",\\\\\\\"don't include userInstallations on toJson for user\\\\\\\",\\\\\\\"added lastCode to User class + new error\\\\\\\",\\\\\\\"lastLogin attribute added to User class\\\\\\\",\\\\\\\"refactor\\\\\\\",\\\\\\\"on exception on login, throw it so we can handle it in UI\\\\\\\",\\\\\\\"added simple usertype getter\\\\\\\",\\\\\\\"bumped version\\\\\\\",\\\\\\\"pub upgrade\\\\\\\",\\\\\\\"customer as class in JsonSerializable\\\\\\\",\\\\\\\"more specific userpermissions\\\\\\\",\\\\\\\"support for new params on transformer for limiting log\\\\\\\",\\\\\\\"removed limitLog params\\\\\\\",\\\\\\\"bumped version\\\\\\\",\\\\\\\"Added BiocloudError\\\\\\\",\\\\\\\"cleaning up todos\\\\\\\",\\\\\\\"pumped version\\\\\\\",\\\\\\\"upgraded pubspec\\\\\\\",\\\\\\\"downgraded dependency\\\\\\\",\\\\\\\"API methods for updating/removing UserCustomer\\\\\\\",\\\\\\\"getAllUnits method (for cirrus)\\\\\\\",\\\\\\\"Added firmware class and publishedFirmware variable for unit\\\\\\\",\\\\\\\"Added api for publishfirmware / getfirmwares\\\\\\\",\\\\\\\"\\\\\\\"]\\\"},\\\"scm/input:Git:/Users/chris/Coding/bioservo/ironconnect\\\":{\\\"version\\\":1,\\\"value\\\":\\\"[\\\\\\\"small fix\\\\\\\",\\\\\\\"set targetSdk to 29 as required by play store\\\\\\\",\\\\\\\"generated new icon\\\\\\\",\\\\\\\"upgraded embedding to v2\\\\\\\",\\\\\\\"replaced stack-snackbar with oktoast library\\\\\\\",\\\\\\\"padding fix preferences\\\\\\\",\\\\\\\"navigator.push replaced by utility push(context, child) method\\\\\\\",\\\\\\\"cleaning up todos\\\\\\\",\\\\\\\"toast on notched iPhones now has proper padding\\\\\\\",\\\\\\\"big refactor to bioflutterlib\\\\\\\",\\\\\\\"renaming and refactor to bioflutterlib\\\\\\\",\\\\\\\"MainActivity was missing line after upgrading flutter embedding\\\\\\\",\\\\\\\"removed intl packages that we don't use\\\\\\\",\\\\\\\"\\\\\\\"]\\\"},\\\"scm/input:Git:/Users/chris/Coding/bioservo/ironconnectlib\\\":{\\\"version\\\":1,\\\"value\\\":\\\"[\\\\\\\"refactoring\\\\\\\",\\\\\\\"\\\\\\\\\\\\\\\"Prominent disclosure\\\\\\\\\\\\\\\" for location permissions\\\\\\\",\\\\\\\"appbarlisttile widget and style fix\\\\\\\",\\\\\\\"disabled autocorrect for all text(form)fields\\\\\\\",\\\\\\\"translation fix\\\\\\\",\\\\\\\"started adding loading indicators in config\\\\\\\",\\\\\\\"bumped version\\\\\\\",\\\\\\\"updated biocloudlib dependency\\\\\\\",\\\\\\\"pub upgrade \\\\\\\",\\\\\\\"added loading indicators in config, e.g. overwrite profiles\\\\\\\",\\\\\\\"translation, comment\\\\\\\",\\\\\\\"more helpful connection failed message\\\\\\\",\\\\\\\"bumped version\\\\\\\",\\\\\\\"added translation\\\\\\\",\\\\\\\"clarified location permissions and added privacy policy in-app\\\\\\\",\\\\\\\"replaced stack-snackbar with oktoast library\\\\\\\",\\\\\\\"experimental method for try catch\\\\\\\",\\\\\\\"refactoring\\\\\\\",\\\\\\\"bumped version and added git dependency\\\\\\\",\\\\\\\"null check\\\\\\\",\\\\\\\"Big refactor of PopupMenu\\\\\\\",\\\\\\\"cleaning\\\\\\\",\\\\\\\"navigator.push replaced by utility push(context, child) method\\\\\\\",\\\\\\\"refactor: more usage of showD() and pop() utility methods\\\\\\\",\\\\\\\"renamed notif() to toast()\\\\\\\",\\\\\\\"severe infinity loop fix (caused by recent commits)\\\\\\\",\\\\\\\"better error-handling if no internet\\\\\\\",\\\\\\\"refactor\\\\\\\",\\\\\\\"added toast feedback\\\\\\\",\\\\\\\"textoverflow fixp\\\\\\\",\\\\\\\"cleaning up todos\\\\\\\",\\\\\\\"bumped version\\\\\\\",\\\\\\\"toast on notched iPhones now has proper padding\\\\\\\",\\\\\\\"color fixes\\\\\\\",\\\\\\\"new pubspec.lock\\\\\\\",\\\\\\\"refactor\\\\\\\",\\\\\\\"\\\\\\\",\\\\\\\"big refactor to bioflutterlib\\\\\\\",\\\\\\\"big refactor to bioflutterlib\\\\\\\",\\\\\\\"renaming and refactor to bioflutterlib\\\\\\\",\\\\\\\"added separate widget tree for BleScanner and cleaned\\\\\\\",\\\\\\\"removed intl packages that we don't use\\\\\\\",\\\\\\\"\\\\\\\"]\\\"},\\\"scm/input:Git:/Users/chris/Coding/bioservo/stratus\\\":{\\\"version\\\":1,\\\"value\\\":\\\"[\\\\\\\"pubspec fix\\\\\\\",\\\\\\\"\\\\\\\"]\\\"},\\\"scm/input:Git:/Users/chris/Coding/bioservo/transformer\\\":{\\\"version\\\":1,\\\"value\\\":\\\"[\\\\\\\"testing\\\\\\\",\\\\\\\"undid last commit\\\\\\\",\\\\\\\"testing\\\\\\\",\\\\\\\"removed trick for reusing controller\\\\\\\",\\\\\\\"return customer on getUser(s)\\\\\\\",\\\\\\\"if user customer changed, delete existing installations\\\\\\\",\\\\\\\"test\\\\\\\",\\\\\\\"test\\\\\\\",\\\\\\\"removed test changes\\\\\\\",\\\\\\\"big refactor of testing: now with reusable methods\\\\\\\",\\\\\\\"onChange customer for superUser, remove UserInstallations\\\\\\\",\\\\\\\"incorrect userId reference..\\\\\\\",\\\\\\\"updated broken test\\\\\\\",\\\\\\\"removed \\\\\\\\\\\\\\\"new\\\\\\\\\\\\\\\" keyword\\\\\\\",\\\\\\\"lastCodeRequest timestamp for users\\\\\\\",\\\\\\\"always return lastCode for GET on UserController \\\\\\\",\\\\\\\"testing\\\\\\\",\\\\\\\"deleted migration\\\\\\\",\\\\\\\"lastCode omitted for certain UserTypes (e.g. bioservoUser)\\\\\\\",\\\\\\\"If recovery code expired, show appropriate error.\\\\\\\",\\\\\\\"added lastCodeRequest to returning properties in recovery controller\\\\\\\",\\\\\\\"GET /user returns bioservousers only if requester canBioservoUser\\\\\\\",\\\\\\\"added relation between log and customer + test\\\\\\\",\\\\\\\"customerId param for units to get only log for given customer\\\\\\\",\\\\\\\"added customerId param for operator and glove also\\\\\\\",\\\\\\\"copy pasting to installation unit controller\\\\\\\",\\\\\\\"get customerId through installationId instead\\\\\\\",\\\\\\\"get customerId for log filtering using installationId\\\\\\\",\\\\\\\"post log sets customerId according to item's installation's customer id \\\\\\\",\\\\\\\"GET single unit bool arg for limitedLog\\\\\\\",\\\\\\\"limitLogToCurrentCustomer parameter unit/glove/op controller\\\\\\\",\\\\\\\"removed unnecessary parameter\\\\\\\",\\\\\\\"get customerId through user making request\\\\\\\",\\\\\\\"removed limitLog param\\\\\\\",\\\\\\\"AnalysisFindController only looks within the given installation\\\\\\\",\\\\\\\"cleaning, refactor\\\\\\\",\\\\\\\"updated pubspec (mqtt_client was not compatible with biocloudlib)\\\\\\\",\\\\\\\"added UserCustomerController\\\\\\\",\\\\\\\"updated tests\\\\\\\",\\\\\\\"cleaning\\\\\\\",\\\\\\\"comment\\\\\\\",\\\\\\\"allow all for CORS\\\\\\\",\\\\\\\"Users without canBioservoUser flag can't create bioservoUsers. \\\\\\\",\\\\\\\"hal and kim templates added by default to new installations\\\\\\\",\\\\\\\"\\\\\\\",\\\\\\\"hal and kim templates added by default to new installations\\\\\\\",\\\\\\\"refactor: avoid passing ManagedContext as arg when we can access it globally instead\\\\\\\",\\\\\\\"cleaning\\\\\\\",\\\\\\\"\\\\\\\\n\\\\\\\",\\\\\\\"cleaning\\\\\\\"]\\\"},\\\"memento/gettingStartedService\\\":{\\\"version\\\":1,\\\"value\\\":\\\"{\\\\\\\"pickColorTheme\\\\\\\":{\\\\\\\"done\\\\\\\":true},\\\\\\\"commandPaletteTask\\\\\\\":{\\\\\\\"done\\\\\\\":true},\\\\\\\"pickAFolderTask-Mac\\\\\\\":{\\\\\\\"done\\\\\\\":true},\\\\\\\"terminal\\\\\\\":{\\\\\\\"done\\\\\\\":true},\\\\\\\"settings\\\\\\\":{\\\\\\\"done\\\\\\\":true}}\\\"},\\\"scm/input:Git:/Users/chris/Coding/hokaido/dart-epub\\\":{\\\"version\\\":1,\\\"value\\\":\\\"[\\\\\\\"init \\\\\\\",\\\\\\\"not capitalized variable names\\\\\\\",\\\\\\\"\\\\\\\"]\\\"},\\\"scm/input:Git:/Users/chris/Coding/hokaido/flutter_html\\\":{\\\"version\\\":1,\\\"value\\\":\\\"[\\\\\\\"commented away\\\\\\\",\\\\\\\"Merge branch 'master' of github.com:Sub6Resources/flutter_html\\\\\\\"]\\\"},\\\"scm/input:Git:/Users/chris/Coding/hokaido/packages.flutter\\\":{\\\"version\\\":1,\\\"value\\\":\\\"[\\\\\\\"\\\\\\\"]\\\"},\\\"scm/input:Git:/Users/chris/Coding/pki_pilot/Ejbca\\\":{\\\"version\\\":1,\\\"value\\\":\\\"[\\\\\\\"\\\\\\\"]\\\"},\\\"scm/input:Git:/Users/chris/Coding/pki_pilot/pkipilotlib\\\":{\\\"version\\\":1,\\\"value\\\":\\\"[\\\\\\\"basic 2FA\\\\\\\",\\\\\\\"\\\\\\\",\\\\\\\"api methods for OTP, generating secret etc. \\\\\\\",\\\\\\\"\\\\\\\"]\\\"},\\\"scm/input:Git:/Users/chris/Coding/pki_pilot/pkipilotportal\\\":{\\\"version\\\":1,\\\"value\\\":\\\"[\\\\\\\"deleted dead code\\\\\\\",\\\\\\\"basic cleanup\\\\\\\",\\\\\\\"Foundation with sidebar and dashboard\\\\\\\",\\\\\\\"Foundation with Navigator 2.0 routing\\\\\\\",\\\\\\\"basic 2FA\\\\\\\",\\\\\\\"\\\\\\\"]\\\"},\\\"scm/input:Git:/Users/chris/Coding/pki_pilot/pkipilotserver\\\":{\\\"version\\\":1,\\\"value\\\":\\\"[\\\\\\\"bootstrapcontroller should set useOTP = false for admin\\\\\\\",\\\\\\\"testing\\\\\\\",\\\\\\\"useOTP = false on POST user\\\\\\\",\\\\\\\"added separate controller for setting otp secret\\\\\\\",\\\\\\\"enabled globalContext and started using it \\\\\\\",\\\\\\\"otp controller without username arg\\\\\\\",\\\\\\\"can validate OTP code without OTP enabled, so that we can ensure that the user has a correct seed setup\\\\\\\",\\\\\\\"We must explicitly fetch otpSecret field because it is omitted by default\\\\\\\",\\\\\\\"test setting isGoogle to true for OTP generator\\\\\\\",\\\\\\\"Return correct code for debugging\\\\\\\",\\\\\\\"try adding isGoogle parameter again\\\\\\\",\\\\\\\"try using different OTP package\\\\\\\",\\\\\\\"added some params to TOTP generation method, let's see if it works\\\\\\\",\\\\\\\"trying with other auth app\\\\\\\",\\\\\\\"different algorithm\\\\\\\",\\\\\\\"back to sha1\\\\\\\",\\\\\\\"test\\\\\\\",\\\\\\\"test\\\\\\\",\\\\\\\"test\\\\\\\",\\\\\\\"test\\\\\\\",\\\\\\\"switched OTP dependency to git in case it works better\\\\\\\",\\\\\\\"disabled sha1 again\\\\\\\",\\\\\\\"test\\\\\\\",\\\\\\\"test\\\\\\\",\\\\\\\"test\\\\\\\",\\\\\\\"test\\\\\\\",\\\\\\\"test\\\\\\\",\\\\\\\"test\\\\\\\",\\\\\\\"test\\\\\\\",\\\\\\\"test with other\\\\\\\",\\\\\\\"test\\\\\\\",\\\\\\\"testing both packages\\\\\\\",\\\\\\\"test\\\\\\\",\\\\\\\"test\\\\\\\",\\\\\\\"test\\\\\\\",\\\\\\\"test\\\\\\\",\\\\\\\"test\\\\\\\",\\\\\\\"test\\\\\\\",\\\\\\\"\\\\\\\"]\\\"},\\\"scm/input:Git:/Users/chris/Coding/pki_pilot/pkipilottool\\\":{\\\"version\\\":1,\\\"value\\\":\\\"[\\\\\\\"\\\\\\\"]\\\"},\\\"scm/input:Git:/Users/chris/Coding/inspiration/epub_viewer\\\":{\\\"version\\\":1,\\\"value\\\":\\\"[\\\\\\\"\\\\\\\"]\\\"},\\\"scm/input:Git:/Users/chris/Coding/inspiration/natrium_wallet_flutter\\\":{\\\"version\\\":1,\\\"value\\\":\\\"[\\\\\\\"\\\\\\\"]\\\"},\\\"scm/input:Git:/Users/chris/.pub-cache/git/ironconnectlib-2be9ce87dc840f0eb9da9523342ad1ccf84482c5\\\":{\\\"version\\\":1,\\\"value\\\":\\\"[\\\\\\\"\\\\\\\"]\\\"},\\\"scm/input:Git:/Users/chris/.pub-cache/git/biocloudlib-cd06c127b9822334b1520dc27ced2c425a4a953a\\\":{\\\"version\\\":1,\\\"value\\\":\\\"[\\\\\\\"\\\\\\\"]\\\"},\\\"scm/input:Git:/Users/chris/Coding/hokaido/epub_view\\\":{\\\"version\\\":1,\\\"value\\\":\\\"[\\\\\\\"init\\\\\\\",\\\\\\\"disabled exception being thrown\\\\\\\",\\\\\\\"selecting something in ToC pops context\\\\\\\",\\\\\\\"buildElement parameter to pass external Widget into tree\\\\\\\",\\\\\\\"normal scrollcontroller to remember epub position\\\\\\\",\\\\\\\"\\\\\\\"]\\\"},\\\"scm/input:Git:/Users/chris/Coding/inspiration/feature_discovery\\\":{\\\"version\\\":1,\\\"value\\\":\\\"[\\\\\\\"\\\\\\\"]\\\"},\\\"scm/input:Git:/c:/Users/Chris/Documents/Coding/utilitiesapp\\\":{\\\"version\\\":1,\\\"value\\\":\\\"[\\\\\\\"init\\\\\\\",\\\\\\\"\\\\\\\"]\\\"},\\\"scm/input:Git:/c:/Users/Chris/Documents/Coding/bioservo/utilitiesapp\\\":{\\\"version\\\":1,\\\"value\\\":\\\"[\\\\\\\"ran 'flutter create .'\\\\\\\",\\\\\\\"foundation with drawer, preferences\\\\\\\",\\\\\\\"initial test graph\\\\\\\",\\\\\\\"pub get\\\\\\\",\\\\\\\"experimenting, switching machine\\\\\\\",\\\\\\\"basic simulation of csv values\\\\\\\",\\\\\\\"\\\\\\\"]\\\"},\\\"scm/input:Git:/c:/Users/Chris/Documents/Coding/bioservo/biocloudlib\\\":{\\\"version\\\":1,\\\"value\\\":\\\"[\\\\\\\"\\\\\\\"]\\\"},\\\"scm/input:Git:/c:/Users/Chris/Documents/Coding/bioservo/ironconnectlib\\\":{\\\"version\\\":1,\\\"value\\\":\\\"[\\\\\\\"\\\\\\\"]\\\"},\\\"scm/input:Git:/c:/Users/Chris/Documents/Coding/bioservo/ironconnectpro\\\":{\\\"version\\\":1,\\\"value\\\":\\\"[\\\\\\\"\\\\\\\"]\\\"},\\\"scm/input:Git:/c:/Users/Chris/Documents/Coding/bioservo/ironconnect\\\":{\\\"version\\\":1,\\\"value\\\":\\\"[\\\\\\\"\\\\\\\"]\\\"},\\\"scm/input:Git:/c:/Users/Chris/Documents/Coding/bioservo/transformer\\\":{\\\"version\\\":1,\\\"value\\\":\\\"[\\\\\\\"\\\\\\\"]\\\"},\\\"scm/input:Git:/c:/Users/Chris/Documents/Coding/bioservo/stratus\\\":{\\\"version\\\":1,\\\"value\\\":\\\"[\\\\\\\"\\\\\\\"]\\\"},\\\"memento/workbench.editor.keybindings\\\":{\\\"version\\\":1,\\\"value\\\":\\\"{\\\\\\\"searchHistory\\\\\\\":[\\\\\\\"select tab\\\\\\\",\\\\\\\"save a\\\\\\\",\\\\\\\"1\\\\\\\",\\\\\\\"openEd\\\\\\\",\\\\\\\"openEditorAt\\\\\\\",\\\\\\\"openEditorAtI\\\\\\\",\\\\\\\"close\\\\\\\",\\\\\\\"close other\\\\\\\",\\\\\\\"toggle line\\\\\\\",\\\\\\\"t\\\\\\\",\\\\\\\"terminal\\\\\\\",\\\\\\\"toggle inte\\\\\\\",\\\\\\\"rename\\\\\\\",\\\\\\\"lef\\\\\\\",\\\\\\\"tab to left\\\\\\\",\\\\\\\"move\\\\\\\",\\\\\\\"next \\\\\\\",\\\\\\\"next ta\\\\\\\",\\\\\\\"next tab\\\\\\\",\\\\\\\"next\\\\\\\",\\\\\\\"ne\\\\\\\",\\\\\\\"previo\\\\\\\",\\\\\\\"ta\\\\\\\",\\\\\\\"tab\\\\\\\",\\\\\\\"next editor\\\\\\\",\\\\\\\"focus edi\\\\\\\",\\\\\\\"focus editor\\\\\\\",\\\\\\\"editor\\\\\\\",\\\\\\\"select\\\\\\\",\\\\\\\"\\\\\\\\\\\\\\\"cmd+k v\\\\\\\\\\\\\\\"\\\\\\\",\\\\\\\"\\\\\\\\\\\\\\\"shift+cmd+i\\\\\\\\\\\\\\\"\\\\\\\",\\\\\\\"\\\\\\\\\\\\\\\"cmd+i\\\\\\\\\\\\\\\"\\\\\\\",\\\\\\\"\\\\\\\\\\\\\\\"backspace\\\\\\\\\\\\\\\"\\\\\\\",\\\\\\\"ital\\\\\\\",\\\\\\\"italic\\\\\\\",\\\\\\\"bold\\\\\\\",\\\\\\\"create\\\\\\\",\\\\\\\"create new\\\\\\\",\\\\\\\"new folder\\\\\\\",\\\\\\\"new file\\\\\\\",\\\\\\\"files \\\\\\\",\\\\\\\"files and fo\\\\\\\",\\\\\\\"files and fol\\\\\\\"]}\\\"},\\\"scm/input:Git:/Users/chris/Coding/bioservo/utilitiesapp\\\":{\\\"version\\\":1,\\\"value\\\":\\\"[\\\\\\\"simulating real data test\\\\\\\",\\\\\\\"big refactor to bioflutterlib\\\\\\\",\\\\\\\"renaming and refactor to bioflutterlib\\\\\\\",\\\\\\\"\\\\\\\"]\\\"},\\\"scm/input:Git:/c:/Users/Chris/Documents/Coding/Hokaido\\\":{\\\"version\\\":1,\\\"value\\\":\\\"[\\\\\\\"\\\\\\\"]\\\"},\\\"fileBasedRecommendations/promptedFileExtensions\\\":{\\\"version\\\":1,\\\"value\\\":\\\"[\\\\\\\"pas\\\\\\\",\\\\\\\"dfm\\\\\\\",\\\\\\\"rst\\\\\\\"]\\\"},\\\"scm/input:Git:/Users/chris/Coding/hokaido/hokaido_app\\\":{\\\"version\\\":1,\\\"value\\\":\\\"[\\\\\\\"added some \\\\\\\\\\\\\\\"URL type\\\\\\\\\\\\\\\" in Xcode to enable Google Drive backup on iOS\\\\\\\",\\\\\\\"poor use of activeBook to get id of not-yet-created-book\\\\\\\",\\\\\\\"\\\\\\\",\\\\\\\"poor use of activeBook to get id of not-yet-created-book\\\\\\\",\\\\\\\"slight mod of flashcard algo: less new cards\\\\\\\",\\\\\\\"null-call-fix and batch for adding lookup websites\\\\\\\",\\\\\\\"Added statistics function which tracks points received on doing flashcards over time (with calendarview)\\\\\\\",\\\\\\\"on import zip, delete the contents in appdir, not the folder itself \\\\\\\",\\\\\\\"bugfixes on \\\\\\\\\\\\\\\"points\\\\\\\\\\\\\\\" being null etc\\\\\\\",\\\\\\\"cleaning + sort target/source as lang name\\\\\\\",\\\\\\\"adjust daily goal\\\\\\\",\\\\\\\"cleaning\\\\\\\",\\\\\\\"\\\\\\\",\\\\\\\"cleaning\\\\\\\",\\\\\\\"change between epub books actually does something\\\\\\\",\\\\\\\"\\\\\\\",\\\\\\\"change between epub books actually does something\\\\\\\",\\\\\\\"epub book switch was still faulty, new attempt here\\\\\\\",\\\\\\\"show loading dialog on change book\\\\\\\",\\\\\\\"synonyms + tenses in flashcards\\\\\\\",\\\\\\\"showLoadingDialog on open book, not only on change\\\\\\\",\\\\\\\"bugfix: first saved entry would cause a scroll-down\\\\\\\",\\\\\\\"fixed timer save epub scrollposition every 10 sec\\\\\\\",\\\\\\\"stats cleaned + created\\\\\\\",\\\\\\\"fuzzy duplicate finder \\\\\\\",\\\\\\\"cleaning, toast on reached daily goal\\\\\\\",\\\\\\\"BottomNotch padding toast()\\\\\\\",\\\\\\\"scan text using OCR \\\\\\\",\\\\\\\"duplicate lookup in readerview\\\\\\\",\\\\\\\"lookup sentence\\\\\\\",\\\\\\\"exclude the edited word from duplicate checker on edit entry\\\\\\\",\\\\\\\"suspended explanation\\\\\\\",\\\\\\\"dependency updates to make the app run\\\\\\\",\\\\\\\"dropdown title calendarview\\\\\\\",\\\\\\\"updated db migration strategy\\\\\\\",\\\\\\\"HomePage -> NavPage\\\\\\\",\\\\\\\"CalendarView through navStore rather than push()\\\\\\\",\\\\\\\"open list of entries on tapped calendary day\\\\\\\",\\\\\\\"enabled flutter_localizations again, not breaking anymore\\\\\\\",\\\\\\\"backup daily without await\\\\\\\",\\\\\\\"\\\\\\\",\\\\\\\"backup daily without await\\\\\\\",\\\\\\\"prefs for daily backup\\\\\\\",\\\\\\\"\\\\\\\",\\\\\\\"prefs for daily backup\\\\\\\",\\\\\\\"keep previous backup on drive when uploading new one\\\\\\\",\\\\\\\"cleaning\\\\\\\",\\\\\\\"Removed Firebase MLVision for OCR, didn't work on iOS for now\\\\\\\",\\\\\\\"rename\\\\\\\",\\\\\\\"\\\\\\\"]\\\"},\\\"github-Christian-Martensson\\\":{\\\"version\\\":1,\\\"value\\\":\\\"[{\\\\\\\"id\\\\\\\":\\\\\\\"vscode.github\\\\\\\",\\\\\\\"name\\\\\\\":\\\\\\\"GitHub\\\\\\\"}]\\\"},\\\"scm/input:Git:/c:/Users/Chris/Documents/Coding/inspiration/MPFlutterChart\\\":{\\\"version\\\":1,\\\"value\\\":\\\"[\\\\\\\"\\\\\\\"]\\\"},\\\"scm/input:Git:/c:/Users/Chris/Documents/Coding/inspiration/fl_chart\\\":{\\\"version\\\":1,\\\"value\\\":\\\"[\\\\\\\"\\\\\\\"]\\\"},\\\"scm/input:Git:/Users/chris/Coding/inspiration/graphql-flutter\\\":{\\\"version\\\":1,\\\"value\\\":\\\"[\\\\\\\"\\\\\\\"]\\\"},\\\"scm/input:Git:/Users/chris/.pub-cache/git/ironconnectlib-73b3be81aeda01c857382d6a00aa47383c3f16c2\\\":{\\\"version\\\":1,\\\"value\\\":\\\"[\\\\\\\"\\\\\\\"]\\\"},\\\"scm/input:Git:/c:/Users/Chris/Documents/Coding/flutter\\\":{\\\"version\\\":1,\\\"value\\\":\\\"[\\\\\\\"\\\\\\\"]\\\"},\\\"scm/input:Git:/Users/chris/Coding/bioservo/cirrus\\\":{\\\"version\\\":1,\\\"value\\\":\\\"[\\\\\\\"Foundation\\\\\\\",\\\\\\\"login + table for filtering and sorting units on serial, label and firmware\\\\\\\",\\\\\\\"renaming and refactor to bioflutterlib\\\\\\\",\\\\\\\"listing units and firmwares fully functional\\\\\\\",\\\\\\\"Units can now be selected\\\\\\\",\\\\\\\"\\\\\\\",\\\\\\\"Units can now be selected\\\\\\\",\\\\\\\"Cleaning, fixed some sorting bugs etc. \\\\\\\",\\\\\\\"Updated description (showed in links to website) \\\\\\\",\\\\\\\"\\\\\\\"]\\\"},\\\"scm/input:Git:/Users/chris/Coding/validicity/validicityapp\\\":{\\\"version\\\":1,\\\"value\\\":\\\"[\\\\\\\"Big clean and refactor. Updated dependencies. \\\\\\\",\\\\\\\"ran \\\\\\\\\\\\\\\"flutter create .\\\\\\\\\\\\\\\" to make things work on iOS\\\\\\\",\\\\\\\"basic dialog after scan sample\\\\\\\",\\\\\\\"redesigned list of sample view and chain_view\\\\\\\",\\\\\\\"Cleaning, refactor\\\\\\\",\\\\\\\"save location on scan and then display using google maps\\\\\\\",\\\\\\\"everything working, including maps, on android\\\\\\\",\\\\\\\"disabled location features for testflight\\\\\\\",\\\\\\\"iOS force square crop profile pic\\\\\\\",\\\\\\\"bumped version and removed stuff for release\\\\\\\",\\\\\\\"added splash screen etc. ios\\\\\\\",\\\\\\\"\\\\\\\"]\\\"},\\\"scm/input:Git:/Users/chris/Coding/validicity/validicityapplib\\\":{\\\"version\\\":1,\\\"value\\\":\\\"[\\\\\\\"Big clean and refactor. Updated dependencies. \\\\\\\",\\\\\\\"renaming\\\\\\\",\\\\\\\"Cleaning, added utility methods\\\\\\\",\\\\\\\"Cleaning, refactor\\\\\\\",\\\\\\\"fixed progressindicator widget\\\\\\\",\\\\\\\"bumped version\\\\\\\",\\\\\\\"\\\\\\\"]\\\"},\\\"scm/input:Git:/Users/chris/Coding/validicity/validicitylib\\\":{\\\"version\\\":1,\\\"value\\\":\\\"[\\\\\\\"clean up, removed Hive dependency\\\\\\\",\\\\\\\"Updates to classes for avatar etc. + key generation for mobile\\\\\\\",\\\\\\\"Cleaning, refactor\\\\\\\",\\\\\\\"added longitude and latitude to sample\\\\\\\",\\\\\\\"added error\\\\\\\",\\\\\\\"Exception handling fix\\\\\\\",\\\\\\\"bumped version\\\\\\\",\\\\\\\"\\\\\\\"]\\\"},\\\"scm/input:Git:/Users/chris/Coding/bioservo/bioflutterlib\\\":{\\\"version\\\":1,\\\"value\\\":\\\"[\\\\\\\"init commit\\\\\\\",\\\\\\\"big refactor to bioflutterlib\\\\\\\",\\\\\\\"drawerheader added \\\\\\\\n\\\\\\\",\\\\\\\"added widget\\\\\\\",\\\\\\\"fixed drawerheader asset import\\\\\\\",\\\\\\\"removed intl packages that we don't use\\\\\\\",\\\\\\\"added generics for SortOption\\\\\\\",\\\\\\\"popupmenu can take a child widget, not only icon\\\\\\\",\\\\\\\"added customServerAddress as parameter to DrawerHeader\\\\\\\",\\\\\\\"updated 18n_extension dependency to master, fixed nullsafety build eror\\\\\\\",\\\\\\\"don't ping() on web platform\\\\\\\",\\\\\\\"changed to i18n_extension on git (not local)\\\\\\\",\\\\\\\"\\\\\\\"]\\\"},\\\"scm/input:Git:/Users/chris/Coding/validicity/validicityserver\\\":{\\\"version\\\":1,\\\"value\\\":\\\"[\\\\\\\"cleaning, started using globalContext to avoid passing context everywhere\\\\\\\",\\\\\\\"added User-Sample relation + avatar string attribute to user\\\\\\\",\\\\\\\"On sample submission, set requester's id on the sample\\\\\\\",\\\\\\\"user_self_controller can update name and username\\\\\\\",\\\\\\\"lowered required dart version in .yaml\\\\\\\",\\\\\\\"removed faulty parameter\\\\\\\",\\\\\\\"test\\\\\\\",\\\\\\\"self_controller test + don't emit avatar by default\\\\\\\",\\\\\\\"added comment attribute to [Sample]\\\\\\\",\\\\\\\"comments are nullable\\\\\\\",\\\\\\\"Reusing controllers as variable caused errors on transformer so lets not try it here\\\\\\\",\\\\\\\"sample submission controller fixed, was throwing errors\\\\\\\",\\\\\\\"comment does not need to be unique + location string\\\\\\\",\\\\\\\"added longitude and latitude to sample\\\\\\\",\\\\\\\"added user registration endpoint\\\\\\\",\\\\\\\"updated register controller with email\\\\\\\",\\\\\\\"forgot to add name to user\\\\\\\",\\\\\\\"testing\\\\\\\",\\\\\\\"test\\\\\\\",\\\\\\\"testing\\\\\\\",\\\\\\\"test\\\\\\\",\\\\\\\"wrong project id\\\\\\\",\\\\\\\"check if user exists before registering\\\\\\\",\\\\\\\"same as previous for register_controller\\\\\\\",\\\\\\\"incorrect syntax for map fix\\\\\\\",\\\\\\\"fix\\\\\\\",\\\\\\\"added error\\\\\\\",\\\\\\\"\\\\\\\"]\\\"},\\\"scm/input:Git:/Users/chris/Coding/validicity/validicitytool\\\":{\\\"version\\\":1,\\\"value\\\":\\\"[\\\\\\\"\\\\\\\"]\\\"},\\\"scm/input:Git:/Users/chris/Coding/inspiration/dart_postgis\\\":{\\\"version\\\":1,\\\"value\\\":\\\"[\\\\\\\"\\\\\\\"]\\\"},\\\"scm/input:Git:/Users/chris/Coding/validicity/validicityclient\\\":{\\\"version\\\":1,\\\"value\\\":\\\"[\\\\\\\"\\\\\\\"]\\\"},\\\"workbench.view.sync.state.hidden\\\":{\\\"version\\\":1,\\\"value\\\":\\\"[{\\\\\\\"id\\\\\\\":\\\\\\\"workbench.views.sync.merges\\\\\\\",\\\\\\\"isHidden\\\\\\\":false},{\\\\\\\"id\\\\\\\":\\\\\\\"workbench.views.sync.remoteActivity\\\\\\\",\\\\\\\"isHidden\\\\\\\":false},{\\\\\\\"id\\\\\\\":\\\\\\\"workbench.views.sync.machines\\\\\\\",\\\\\\\"isHidden\\\\\\\":false},{\\\\\\\"id\\\\\\\":\\\\\\\"workbench.views.sync.localActivity\\\\\\\",\\\\\\\"isHidden\\\\\\\":true}]\\\"},\\\"http.linkProtectionTrustedDomains\\\":{\\\"version\\\":1,\\\"value\\\":\\\"[\\\\\\\"https://www.dendron.so\\\\\\\"]\\\"},\\\"scm/input:Git:/Users/chris/Coding/bioservo/collector\\\":{\\\"version\\\":1,\\\"value\\\":\\\"[\\\\\\\"\\\\\\\"]\\\"},\\\"scm/input:Git:/Users/chris/Coding/inspiration/table_calendar\\\":{\\\"version\\\":1,\\\"value\\\":\\\"[\\\\\\\"\\\\\\\"]\\\"},\\\"scm/input:Git:/Users/chris/Coding/inspiration/flutter_heatmap_calendar\\\":{\\\"version\\\":1,\\\"value\\\":\\\"[\\\\\\\"\\\\\\\"]\\\"},\\\"scm/input:Git:/Users/chris/Coding/inspiration/introduction_screen\\\":{\\\"version\\\":1,\\\"value\\\":\\\"[\\\\\\\"\\\\\\\"]\\\"},\\\"scm/input:Git:/Users/chris/Coding/atomind/ether-wallet-flutter\\\":{\\\"version\\\":1,\\\"value\\\":\\\"[\\\\\\\"\\\\\\\"]\\\"},\\\"scm/input:Git:/Users/chris/Coding/inspiration/flutter_hooks\\\":{\\\"version\\\":1,\\\"value\\\":\\\"[\\\\\\\"\\\\\\\"]\\\"},\\\"scm/input:Git:/Users/chris/.pub-cache/git/validicityapplib-1af894924425e21323d275bdf5d4625d1d31c4cb\\\":{\\\"version\\\":1,\\\"value\\\":\\\"[\\\\\\\"\\\\\\\"]\\\"},\\\"scm/input:Git:/Users/chris/Coding/inspiration/samples\\\":{\\\"version\\\":1,\\\"value\\\":\\\"[\\\\\\\"\\\\\\\"]\\\"},\\\"scm/input:Git:/Users/chris/Coding/inspiration/getx\\\":{\\\"version\\\":1,\\\"value\\\":\\\"[\\\\\\\"\\\\\\\"]\\\"},\\\"scm/input:Git:/Users/chris/Coding/inspiration/bloc\\\":{\\\"version\\\":1,\\\"value\\\":\\\"[\\\\\\\"\\\\\\\"]\\\"},\\\"scm/input:Git:/Users/chris/.pub-cache/git/flutter_architecture_samples-71f32b205e71f844f9136731483e2197838acbab\\\":{\\\"version\\\":1,\\\"value\\\":\\\"[\\\\\\\"\\\\\\\"]\\\"},\\\"scm/input:Git:/Users/chris/Coding/atomind/atomind_wallet\\\":{\\\"version\\\":1,\\\"value\\\":\\\"[\\\\\\\"Foundation, still can't send \\\\\\\",\\\\\\\"\\\\\\\"]\\\"},\\\"scm/input:Git:/Users/chris/Coding/atomind/ether_wallet_flutter\\\":{\\\"version\\\":1,\\\"value\\\":\\\"[\\\\\\\"\\\\\\\"]\\\"},\\\"scm/input:Git:/Users/chris/Coding/atomind/persistent_wallet\\\":{\\\"version\\\":1,\\\"value\\\":\\\"[\\\\\\\"Foundation for UI, still hardcoded\\\\\\\",\\\\\\\"More foundation, not worth commiting in parts yet\\\\\\\",\\\\\\\"style fixes for cards, refactoring\\\\\\\",\\\\\\\"\\\\\\\"]\\\"},\\\"scm/input:Git:/Users/chris/Coding/flutter_todo_example\\\":{\\\"version\\\":1,\\\"value\\\":\\\"[\\\\\\\"Initial commit\\\\\\\",\\\\\\\"updated readme and .gitignore\\\\\\\",\\\\\\\"added some comments\\\\\\\",\\\\\\\"\\\\\\\"]\\\"},\\\"scm/input:Git:/Users/chris/Coding/pki_pilot/lib\\\":{\\\"version\\\":1,\\\"value\\\":\\\"[\\\\\\\"\\\\\\\"]\\\"},\\\"scm/input:Git:/Users/chris/Coding/pki_pilot/portal\\\":{\\\"version\\\":1,\\\"value\\\":\\\"[\\\\\\\"\\\\\\\"]\\\"},\\\"scm/input:Git:/Users/chris/Coding/pki_pilot/server\\\":{\\\"version\\\":1,\\\"value\\\":\\\"[\\\\\\\"\\\\\\\"]\\\"},\\\"scm/input:Git:/Users/chris/Coding/pki_pilot/tool\\\":{\\\"version\\\":1,\\\"value\\\":\\\"[\\\\\\\"\\\\\\\"]\\\"},\\\"scm/input:Git:/Users/chris/Coding/nim/prologue\\\":{\\\"version\\\":1,\\\"value\\\":\\\"[\\\\\\\"\\\\\\\"]\\\"},\\\"scm/input:Git:/Users/chris/Coding/nim/shopapp\\\":{\\\"version\\\":1,\\\"value\\\":\\\"[\\\\\\\"\\\\\\\"]\\\"},\\\"scm/input:Git:/Users/chris/Coding/inspiration/aqueduct\\\":{\\\"version\\\":1,\\\"value\\\":\\\"[\\\\\\\"\\\\\\\"]\\\"},\\\"workbench.views.service.panel.4ba08128-7799-4aa5-8459-7e6c4fd62c38.state.hidden\\\":{\\\"version\\\":1,\\\"value\\\":\\\"[{\\\\\\\"id\\\\\\\":\\\\\\\"terminal\\\\\\\",\\\\\\\"isHidden\\\\\\\":false}]\\\"},\\\"scm/input:Git:/Users/chris/Coding/hokaido/i18n_extension\\\":{\\\"version\\\":1,\\\"value\\\":\\\"[\\\\\\\"\\\\\\\"]\\\"},\\\"scm/input:Git:/Users/chris/Coding/hokaido/test/i18n_extension\\\":{\\\"version\\\":1,\\\"value\\\":\\\"[\\\\\\\"\\\\\\\"]\\\"},\\\"scm/input:Git:/Users/chris/Coding/inspiration/web3dart\\\":{\\\"version\\\":1,\\\"value\\\":\\\"[\\\\\\\"\\\\\\\"]\\\"},\\\"scm/input:Git:/Users/chris/Coding/inspiration/robocore\\\":{\\\"version\\\":1,\\\"value\\\":\\\"[\\\\\\\"\\\\\\\"]\\\"},\\\"scm/input:Git:/Users/chris/.oh-my-zsh\\\":{\\\"version\\\":1,\\\"value\\\":\\\"[\\\\\\\"\\\\\\\"]\\\"},\\\"scm/input:Git:/Users/chris/.pub-cache/git/i18n_extension-11f6908693c2f287ff0b232cf949dc36bb99505d\\\":{\\\"version\\\":1,\\\"value\\\":\\\"[\\\\\\\"\\\\\\\"]\\\"},\\\"scm/input:Git:/Users/chris/Coding/packages/i18n_extension\\\":{\\\"version\\\":1,\\\"value\\\":\\\"[\\\\\\\"Removed \\\\\\\\\\\\\\\"nullOk\\\\\\\\\\\\\\\" parameter causing build errors\\\\\\\",\\\\\\\"\\\\\\\"]\\\"},\\\"scm/input:Git:/Users/chris/Coding/inspiration/fl_chart\\\":{\\\"version\\\":1,\\\"value\\\":\\\"[\\\\\\\"\\\\\\\"]\\\"},\\\"scm/input:Git:/Users/chris/Coding/inspiration/fluro\\\":{\\\"version\\\":1,\\\"value\\\":\\\"[\\\\\\\"\\\\\\\"]\\\"},\\\"scm/input:Git:/Users/chris/Coding/inspiration/navigator_20_example\\\":{\\\"version\\\":1,\\\"value\\\":\\\"[\\\\\\\"\\\\\\\"]\\\"},\\\"scm/input:Git:/Users/chris/Coding/inspiration/auto_route_library\\\":{\\\"version\\\":1,\\\"value\\\":\\\"[\\\\\\\"\\\\\\\"]\\\"},\\\"workbench.view.extension.github-pull-requests.state.hidden\\\":{\\\"version\\\":1,\\\"value\\\":\\\"[{\\\\\\\"id\\\\\\\":\\\\\\\"github:login\\\\\\\",\\\\\\\"isHidden\\\\\\\":false},{\\\\\\\"id\\\\\\\":\\\\\\\"prStatus:github\\\\\\\",\\\\\\\"isHidden\\\\\\\":false},{\\\\\\\"id\\\\\\\":\\\\\\\"pr:github\\\\\\\",\\\\\\\"isHidden\\\\\\\":false},{\\\\\\\"id\\\\\\\":\\\\\\\"github:activePullRequest\\\\\\\",\\\\\\\"isHidden\\\\\\\":false},{\\\\\\\"id\\\\\\\":\\\\\\\"issues:github\\\\\\\",\\\\\\\"isHidden\\\\\\\":false},{\\\\\\\"id\\\\\\\":\\\\\\\"github:createPullRequest\\\\\\\",\\\\\\\"isHidden\\\\\\\":false},{\\\\\\\"id\\\\\\\":\\\\\\\"github:compareChanges\\\\\\\",\\\\\\\"isHidden\\\\\\\":false}]\\\"},\\\"scm/input:Git:/Users/chris/Coding/inspiration/foam-template\\\":{\\\"version\\\":1,\\\"value\\\":\\\"[\\\\\\\"\\\\\\\"]\\\"},\\\"scm/input:Git:/Users/chris/.pub-cache/git/dart-otp-a915d2ee4cf14aee357f2c7a2a6a19d7822d2f30\\\":{\\\"version\\\":1,\\\"value\\\":\\\"[\\\\\\\"\\\\\\\"]\\\"},\\\"scm/input:Git:/Users/chris/Library/Application Support/Code/User\\\":{\\\"version\\\":1,\\\"value\\\":\\\"[\\\\\\\"\\\\\\\"]\\\"}}}\"}"}